{
"meta":{"test_sets":[],"test_metrics":[],"learn_metrics":[{"best_value":"Min","name":"Logloss"}],"launch_mode":"Train","parameters":"","iteration_count":1000,"learn_sets":["learn"],"name":"experiment"},
"iterations":[
{"learn":[0.6875004582],"iteration":0,"passed_time":0.1459783398,"remaining_time":145.8323614},
{"learn":[0.6820239101],"iteration":1,"passed_time":0.1518665319,"remaining_time":75.78139941},
{"learn":[0.676359187],"iteration":2,"passed_time":0.1548647217,"remaining_time":51.46670917},
{"learn":[0.6711400007],"iteration":3,"passed_time":0.1576079458,"remaining_time":39.24437851},
{"learn":[0.6655816602],"iteration":4,"passed_time":0.1606593095,"remaining_time":31.97120258},
{"learn":[0.6610788306],"iteration":5,"passed_time":0.1641773139,"remaining_time":27.19870833},
{"learn":[0.6566539756],"iteration":6,"passed_time":0.1670748031,"remaining_time":23.70075421},
{"learn":[0.6520481236],"iteration":7,"passed_time":0.169931344,"remaining_time":21.07148665},
{"learn":[0.646972854],"iteration":8,"passed_time":0.1731624996,"remaining_time":19.06711524},
{"learn":[0.6417720601],"iteration":9,"passed_time":0.1762849023,"remaining_time":17.45220533},
{"learn":[0.6365682317],"iteration":10,"passed_time":0.1783472475,"remaining_time":16.03503889},
{"learn":[0.6318361605],"iteration":11,"passed_time":0.179772956,"remaining_time":14.80130671},
{"learn":[0.6273610134],"iteration":12,"passed_time":0.1813352884,"remaining_time":13.76753305},
{"learn":[0.6238819875],"iteration":13,"passed_time":0.1828546222,"remaining_time":12.87818982},
{"learn":[0.6194416784],"iteration":14,"passed_time":0.1847112315,"remaining_time":12.12937087},
{"learn":[0.6155016119],"iteration":15,"passed_time":0.1869604054,"remaining_time":11.49806494},
{"learn":[0.6110059993],"iteration":16,"passed_time":0.1888060242,"remaining_time":10.9174307},
{"learn":[0.6070508944],"iteration":17,"passed_time":0.1904296367,"remaining_time":10.38899462},
{"learn":[0.6037699865],"iteration":18,"passed_time":0.1916635855,"remaining_time":9.895893544},
{"learn":[0.6002562442],"iteration":19,"passed_time":0.1930187275,"remaining_time":9.457917646},
{"learn":[0.595717368],"iteration":20,"passed_time":0.1943001072,"remaining_time":9.058085949},
{"learn":[0.5918758804],"iteration":21,"passed_time":0.1956940565,"remaining_time":8.699490329},
{"learn":[0.5879567654],"iteration":22,"passed_time":0.1974376898,"remaining_time":8.386809693},
{"learn":[0.5841741587],"iteration":23,"passed_time":0.1990036145,"remaining_time":8.092813655},
{"learn":[0.579712327],"iteration":24,"passed_time":0.2004854573,"remaining_time":7.818932833},
{"learn":[0.5753583457],"iteration":25,"passed_time":0.2017965794,"remaining_time":7.559610319},
{"learn":[0.5717695113],"iteration":26,"passed_time":0.2031211115,"remaining_time":7.319883017},
{"learn":[0.5669664311],"iteration":27,"passed_time":0.2043843617,"remaining_time":7.095057129},
{"learn":[0.563497542],"iteration":28,"passed_time":0.205783529,"remaining_time":6.890200231},
{"learn":[0.5591494096],"iteration":29,"passed_time":0.2277073229,"remaining_time":7.362536775},
{"learn":[0.555774932],"iteration":30,"passed_time":0.2291132146,"remaining_time":7.161635645},
{"learn":[0.5526400316],"iteration":31,"passed_time":0.2305327258,"remaining_time":6.973614954},
{"learn":[0.5490791177],"iteration":32,"passed_time":0.2320368558,"remaining_time":6.799383016},
{"learn":[0.5458698848],"iteration":33,"passed_time":0.2333900619,"remaining_time":6.631023523},
{"learn":[0.5429985679],"iteration":34,"passed_time":0.2348280863,"remaining_time":6.474545809},
{"learn":[0.5397275543],"iteration":35,"passed_time":0.2372153315,"remaining_time":6.352099433},
{"learn":[0.5366225249],"iteration":36,"passed_time":0.2399302061,"remaining_time":6.244669958},
{"learn":[0.5328302866],"iteration":37,"passed_time":0.2417631442,"remaining_time":6.120424862},
{"learn":[0.5303366712],"iteration":38,"passed_time":0.2434186885,"remaining_time":5.998086146},
{"learn":[0.527159933],"iteration":39,"passed_time":0.245097785,"remaining_time":5.88234684},
{"learn":[0.5238654203],"iteration":40,"passed_time":0.2463657024,"remaining_time":5.762553867},
{"learn":[0.5207131527],"iteration":41,"passed_time":0.2477624619,"remaining_time":5.651343773},
{"learn":[0.5168983135],"iteration":42,"passed_time":0.2491334238,"remaining_time":5.54466713},
{"learn":[0.5133289815],"iteration":43,"passed_time":0.2508895896,"remaining_time":5.451146539},
{"learn":[0.511281213],"iteration":44,"passed_time":0.2520243033,"remaining_time":5.34851577},
{"learn":[0.5089494384],"iteration":45,"passed_time":0.2533262006,"remaining_time":5.253765117},
{"learn":[0.5061602692],"iteration":46,"passed_time":0.2546662232,"remaining_time":5.163764058},
{"learn":[0.5030567099],"iteration":47,"passed_time":0.2560178389,"remaining_time":5.077687137},
{"learn":[0.5010752209],"iteration":48,"passed_time":0.2570717064,"remaining_time":4.98928965},
{"learn":[0.4978979659],"iteration":49,"passed_time":0.2584012738,"remaining_time":4.909624203},
{"learn":[0.4951397213],"iteration":50,"passed_time":0.259698003,"remaining_time":4.832419703},
{"learn":[0.492933591],"iteration":51,"passed_time":0.2609903062,"remaining_time":4.758054044},
{"learn":[0.4902057047],"iteration":52,"passed_time":0.2620460816,"remaining_time":4.682219609},
{"learn":[0.4872775819],"iteration":53,"passed_time":0.2637185473,"remaining_time":4.619958255},
{"learn":[0.48457991],"iteration":54,"passed_time":0.2651259465,"remaining_time":4.555345809},
{"learn":[0.4822667354],"iteration":55,"passed_time":0.2665755857,"remaining_time":4.493702731},
{"learn":[0.4801009006],"iteration":56,"passed_time":0.2679693912,"remaining_time":4.433247998},
{"learn":[0.4775165157],"iteration":57,"passed_time":0.26925523,"remaining_time":4.373076321},
{"learn":[0.4746142739],"iteration":58,"passed_time":0.2705313692,"remaining_time":4.314746075},
{"learn":[0.4730876084],"iteration":59,"passed_time":0.2717289648,"remaining_time":4.257087115},
{"learn":[0.4700307436],"iteration":60,"passed_time":0.2729832321,"remaining_time":4.20215172},
{"learn":[0.4678479261],"iteration":61,"passed_time":0.2742359349,"remaining_time":4.148924306},
{"learn":[0.4648085275],"iteration":62,"passed_time":0.275956697,"remaining_time":4.104308334},
{"learn":[0.462011857],"iteration":63,"passed_time":0.2774409807,"remaining_time":4.057574343},
{"learn":[0.4594364319],"iteration":64,"passed_time":0.2787645776,"remaining_time":4.009921232},
{"learn":[0.4567574927],"iteration":65,"passed_time":0.2800141077,"remaining_time":3.962623887},
{"learn":[0.4550445197],"iteration":66,"passed_time":0.2813976306,"remaining_time":3.918567006},
{"learn":[0.4523928703],"iteration":67,"passed_time":0.2824378806,"remaining_time":3.871060363},
{"learn":[0.4499359952],"iteration":68,"passed_time":0.2837428267,"remaining_time":3.828472053},
{"learn":[0.4474825771],"iteration":69,"passed_time":0.2850148563,"remaining_time":3.786625947},
{"learn":[0.4446162752],"iteration":70,"passed_time":0.2861955649,"remaining_time":3.744727885},
{"learn":[0.4421619563],"iteration":71,"passed_time":0.2874476089,"remaining_time":3.704880293},
{"learn":[0.4399419713],"iteration":72,"passed_time":0.2893766305,"remaining_time":3.6746868},
{"learn":[0.437375624],"iteration":73,"passed_time":0.2908134376,"remaining_time":3.639097882},
{"learn":[0.4348021669],"iteration":74,"passed_time":0.2920864042,"remaining_time":3.602398985},
{"learn":[0.4326765414],"iteration":75,"passed_time":0.2932905974,"remaining_time":3.56579621},
{"learn":[0.4301250874],"iteration":76,"passed_time":0.2945665529,"remaining_time":3.530973095},
{"learn":[0.4283324605],"iteration":77,"passed_time":0.2957909795,"remaining_time":3.496401065},
{"learn":[0.4264188357],"iteration":78,"passed_time":0.2970102871,"remaining_time":3.4626136},
{"learn":[0.4239829567],"iteration":79,"passed_time":0.2981711705,"remaining_time":3.428968461},
{"learn":[0.4223472415],"iteration":80,"passed_time":0.2993508663,"remaining_time":3.396338842},
{"learn":[0.4204185449],"iteration":81,"passed_time":0.3006346492,"remaining_time":3.365641561},
{"learn":[0.4187368066],"iteration":82,"passed_time":0.3023829311,"remaining_time":3.340784913},
{"learn":[0.4162914846],"iteration":83,"passed_time":0.3039110787,"remaining_time":3.314077954},
{"learn":[0.4147190173],"iteration":84,"passed_time":0.305098557,"remaining_time":3.284296232},
{"learn":[0.4127953452],"iteration":85,"passed_time":0.3063367241,"remaining_time":3.255718208},
{"learn":[0.4108690494],"iteration":86,"passed_time":0.3075679186,"remaining_time":3.227695514},
{"learn":[0.4094202794],"iteration":87,"passed_time":0.3087632453,"remaining_time":3.199909997},
{"learn":[0.4080835807],"iteration":88,"passed_time":0.3099781173,"remaining_time":3.172922077},
{"learn":[0.4060737027],"iteration":89,"passed_time":0.3111727741,"remaining_time":3.146302494},
{"learn":[0.4042272544],"iteration":90,"passed_time":0.3123934728,"remaining_time":3.120501833},
{"learn":[0.4025426305],"iteration":91,"passed_time":0.3137486422,"remaining_time":3.096562686},
{"learn":[0.4010037621],"iteration":92,"passed_time":0.3156206216,"remaining_time":3.078149504},
{"learn":[0.3986859286],"iteration":93,"passed_time":0.3170035983,"remaining_time":3.055375107},
{"learn":[0.3973017906],"iteration":94,"passed_time":0.3182927174,"remaining_time":3.032156939},
{"learn":[0.3960164833],"iteration":95,"passed_time":0.3194692469,"remaining_time":3.008335408},
{"learn":[0.3946749334],"iteration":96,"passed_time":0.3207148524,"remaining_time":2.985623832},
{"learn":[0.3926828763],"iteration":97,"passed_time":0.3219556944,"remaining_time":2.963306494},
{"learn":[0.3905521485],"iteration":98,"passed_time":0.3232366603,"remaining_time":2.94178011},
{"learn":[0.3891968698],"iteration":99,"passed_time":0.324372599,"remaining_time":2.919353391},
{"learn":[0.3878666553],"iteration":100,"passed_time":0.3256968854,"remaining_time":2.899024752},
{"learn":[0.3865133082],"iteration":101,"passed_time":0.3268736428,"remaining_time":2.877769914},
{"learn":[0.385171642],"iteration":102,"passed_time":0.3285947885,"remaining_time":2.861645876},
{"learn":[0.3836618753],"iteration":103,"passed_time":0.3297521387,"remaining_time":2.840941503},
{"learn":[0.3827976483],"iteration":104,"passed_time":0.3312755299,"remaining_time":2.823729517},
{"learn":[0.3811397756],"iteration":105,"passed_time":0.3325042813,"remaining_time":2.804328561},
{"learn":[0.3800645285],"iteration":106,"passed_time":0.3334709876,"remaining_time":2.783080299},
{"learn":[0.3788865775],"iteration":107,"passed_time":0.3346473376,"remaining_time":2.763939122},
{"learn":[0.3771077383],"iteration":108,"passed_time":0.3358083111,"remaining_time":2.745001883},
{"learn":[0.3755836976],"iteration":109,"passed_time":0.3370313716,"remaining_time":2.726890189},
{"learn":[0.3746522559],"iteration":110,"passed_time":0.337928921,"remaining_time":2.706475773},
{"learn":[0.3729163193],"iteration":111,"passed_time":0.3391168392,"remaining_time":2.688712082},
{"learn":[0.3715688359],"iteration":112,"passed_time":0.340507276,"remaining_time":2.67283145},
{"learn":[0.3707071609],"iteration":113,"passed_time":0.3422128656,"remaining_time":2.659654376},
{"learn":[0.3693237507],"iteration":114,"passed_time":0.3435692131,"remaining_time":2.643989162},
{"learn":[0.3679428373],"iteration":115,"passed_time":0.3448506031,"remaining_time":2.627999424},
{"learn":[0.3658473366],"iteration":116,"passed_time":0.3462714971,"remaining_time":2.613313948},
{"learn":[0.3639053929],"iteration":117,"passed_time":0.3476853924,"remaining_time":2.598800984},
{"learn":[0.3624411792],"iteration":118,"passed_time":0.3489759691,"remaining_time":2.5835952},
{"learn":[0.3607272762],"iteration":119,"passed_time":0.3502411201,"remaining_time":2.56843488},
{"learn":[0.3598996627],"iteration":120,"passed_time":0.3515074736,"remaining_time":2.55351297},
{"learn":[0.3588168845],"iteration":121,"passed_time":0.352717768,"remaining_time":2.538411478},
{"learn":[0.3576804879],"iteration":122,"passed_time":0.3546331644,"remaining_time":2.528563294},
{"learn":[0.3562277961],"iteration":123,"passed_time":0.356526675,"remaining_time":2.518688446},
{"learn":[0.3550395945],"iteration":124,"passed_time":0.3579175295,"remaining_time":2.505422707},
{"learn":[0.3534557914],"iteration":125,"passed_time":0.3592280783,"remaining_time":2.491788416},
{"learn":[0.3523960481],"iteration":126,"passed_time":0.3605018443,"remaining_time":2.478095355},
{"learn":[0.3512789386],"iteration":127,"passed_time":0.3616966168,"remaining_time":2.464058202},
{"learn":[0.3505064238],"iteration":128,"passed_time":0.3629564679,"remaining_time":2.450659562},
{"learn":[0.3492985038],"iteration":129,"passed_time":0.3641447966,"remaining_time":2.436969024},
{"learn":[0.3479671458],"iteration":130,"passed_time":0.3654167617,"remaining_time":2.424024167},
{"learn":[0.346800846],"iteration":131,"passed_time":0.3669456085,"remaining_time":2.412945365},
{"learn":[0.3453418873],"iteration":132,"passed_time":0.3693119094,"remaining_time":2.407469364},
{"learn":[0.3444873643],"iteration":133,"passed_time":0.3708421821,"remaining_time":2.396636789},
{"learn":[0.343096093],"iteration":134,"passed_time":0.3720569865,"remaining_time":2.383920691},
{"learn":[0.3420063205],"iteration":135,"passed_time":0.3733032249,"remaining_time":2.371573429},
{"learn":[0.3406940443],"iteration":136,"passed_time":0.3745354827,"remaining_time":2.359300158},
{"learn":[0.3395428117],"iteration":137,"passed_time":0.3758026989,"remaining_time":2.347405264},
{"learn":[0.3381726673],"iteration":138,"passed_time":0.3770216219,"remaining_time":2.335364147},
{"learn":[0.3371344291],"iteration":139,"passed_time":0.3782950692,"remaining_time":2.323812568},
{"learn":[0.3357301228],"iteration":140,"passed_time":0.3796828617,"remaining_time":2.313103392},
{"learn":[0.3353769977],"iteration":141,"passed_time":0.3810865515,"remaining_time":2.302621558},
{"learn":[0.3342431521],"iteration":142,"passed_time":0.3826128825,"remaining_time":2.293001681},
{"learn":[0.332709013],"iteration":143,"passed_time":0.3839261667,"remaining_time":2.282227769},
{"learn":[0.3311553071],"iteration":144,"passed_time":0.3850816829,"remaining_time":2.270654061},
{"learn":[0.3304782273],"iteration":145,"passed_time":0.3863825357,"remaining_time":2.260073188},
{"learn":[0.3301004088],"iteration":146,"passed_time":0.3870869813,"remaining_time":2.24615779},
{"learn":[0.3287541242],"iteration":147,"passed_time":0.3883190893,"remaining_time":2.235458541},
{"learn":[0.3279374716],"iteration":148,"passed_time":0.3895600559,"remaining_time":2.224936964},
{"learn":[0.326931847],"iteration":149,"passed_time":0.3907713086,"remaining_time":2.214370749},
{"learn":[0.3253366032],"iteration":150,"passed_time":0.3920033721,"remaining_time":2.20404545},
{"learn":[0.3251018299],"iteration":151,"passed_time":0.3927593424,"remaining_time":2.1911837},
{"learn":[0.3242468175],"iteration":152,"passed_time":0.3946183847,"remaining_time":2.184586744},
{"learn":[0.3231953896],"iteration":153,"passed_time":0.3960725585,"remaining_time":2.175827172},
{"learn":[0.3222226877],"iteration":154,"passed_time":0.397410402,"remaining_time":2.166527675},
{"learn":[0.3217041977],"iteration":155,"passed_time":0.3987226772,"remaining_time":2.15719192},
{"learn":[0.3209583559],"iteration":156,"passed_time":0.3999286492,"remaining_time":2.147387588},
{"learn":[0.3195005693],"iteration":157,"passed_time":0.4010939215,"remaining_time":2.137475202},
{"learn":[0.3187807625],"iteration":158,"passed_time":0.4023001183,"remaining_time":2.127889305},
{"learn":[0.3179006806],"iteration":159,"passed_time":0.4035273826,"remaining_time":2.118518758},
{"learn":[0.3169085297],"iteration":160,"passed_time":0.4048226594,"remaining_time":2.109603797},
{"learn":[0.3158435725],"iteration":161,"passed_time":0.4065570911,"remaining_time":2.103054582},
{"learn":[0.3147060633],"iteration":162,"passed_time":0.4081261348,"remaining_time":2.095715183},
{"learn":[0.3136503479],"iteration":163,"passed_time":0.4094498367,"remaining_time":2.087195509},
{"learn":[0.3129111884],"iteration":164,"passed_time":0.4108445706,"remaining_time":2.079122524},
{"learn":[0.3120675733],"iteration":165,"passed_time":0.4121373229,"remaining_time":2.070617634},
{"learn":[0.3111850342],"iteration":166,"passed_time":0.4134389111,"remaining_time":2.062243191},
{"learn":[0.3101542728],"iteration":167,"passed_time":0.414717279,"remaining_time":2.053837953},
{"learn":[0.3091012652],"iteration":168,"passed_time":0.4160827865,"remaining_time":2.045945536},
{"learn":[0.3080053208],"iteration":169,"passed_time":0.4173783315,"remaining_time":2.037788324},
{"learn":[0.307000724],"iteration":170,"passed_time":0.4187032251,"remaining_time":2.029853647},
{"learn":[0.3060049452],"iteration":171,"passed_time":0.4207078305,"remaining_time":2.025267928},
{"learn":[0.3053166905],"iteration":172,"passed_time":0.42212754,"remaining_time":2.017916044},
{"learn":[0.3042617381],"iteration":173,"passed_time":0.4235043254,"remaining_time":2.010428579},
{"learn":[0.3037673726],"iteration":174,"passed_time":0.4247055239,"remaining_time":2.002183184},
{"learn":[0.3032444952],"iteration":175,"passed_time":0.4259686634,"remaining_time":1.994307833},
{"learn":[0.3021006487],"iteration":176,"passed_time":0.4271995901,"remaining_time":1.986357416},
{"learn":[0.3012169085],"iteration":177,"passed_time":0.4285269869,"remaining_time":1.978927996},
{"learn":[0.3004589168],"iteration":178,"passed_time":0.4297361815,"remaining_time":1.971024609},
{"learn":[0.2999903759],"iteration":179,"passed_time":0.4305690278,"remaining_time":1.961481127},
{"learn":[0.2987520502],"iteration":180,"passed_time":0.431782569,"remaining_time":1.953756486},
{"learn":[0.2977417526],"iteration":181,"passed_time":0.4335944247,"remaining_time":1.948792524},
{"learn":[0.2970939624],"iteration":182,"passed_time":0.4350237525,"remaining_time":1.942155223},
{"learn":[0.2966490975],"iteration":183,"passed_time":0.4360533119,"remaining_time":1.933801644},
{"learn":[0.2956573704],"iteration":184,"passed_time":0.437300624,"remaining_time":1.926486533},
{"learn":[0.2947045999],"iteration":185,"passed_time":0.438550976,"remaining_time":1.91924997},
{"learn":[0.293883853],"iteration":186,"passed_time":0.4398054321,"remaining_time":1.912095274},
{"learn":[0.2936091046],"iteration":187,"passed_time":0.4410695841,"remaining_time":1.905045225},
{"learn":[0.2928064451],"iteration":188,"passed_time":0.4423034837,"remaining_time":1.897926589},
{"learn":[0.2919544986],"iteration":189,"passed_time":0.4436681265,"remaining_time":1.891427276},
{"learn":[0.2910760836],"iteration":190,"passed_time":0.4449141024,"remaining_time":1.884479104},
{"learn":[0.2901479412],"iteration":191,"passed_time":0.4467759368,"remaining_time":1.880182067},
{"learn":[0.2891842736],"iteration":192,"passed_time":0.448258859,"remaining_time":1.874325903},
{"learn":[0.2882371689],"iteration":193,"passed_time":0.4495450386,"remaining_time":1.867697429},
{"learn":[0.2876469373],"iteration":194,"passed_time":0.45071266,"remaining_time":1.860634314},
{"learn":[0.286503785],"iteration":195,"passed_time":0.4519295484,"remaining_time":1.853833454},
{"learn":[0.2858900974],"iteration":196,"passed_time":0.4531764524,"remaining_time":1.847211631},
{"learn":[0.2854168651],"iteration":197,"passed_time":0.4544293447,"remaining_time":1.840668356},
{"learn":[0.2846587822],"iteration":198,"passed_time":0.4557520061,"remaining_time":1.83445908},
{"learn":[0.2836553189],"iteration":199,"passed_time":0.4570891978,"remaining_time":1.828356791},
{"learn":[0.2829402233],"iteration":200,"passed_time":0.4583403718,"remaining_time":1.821959985},
{"learn":[0.2825994718],"iteration":201,"passed_time":0.4601666254,"remaining_time":1.817885976},
{"learn":[0.2817316042],"iteration":202,"passed_time":0.4615942737,"remaining_time":1.812269143},
{"learn":[0.2809635401],"iteration":203,"passed_time":0.4628453761,"remaining_time":1.806004507},
{"learn":[0.2803023024],"iteration":204,"passed_time":0.4641528144,"remaining_time":1.800007256},
{"learn":[0.2793506424],"iteration":205,"passed_time":0.4653681597,"remaining_time":1.793700577},
{"learn":[0.2786059363],"iteration":206,"passed_time":0.4665958278,"remaining_time":1.787490297},
{"learn":[0.2776038303],"iteration":207,"passed_time":0.4678489231,"remaining_time":1.781424746},
{"learn":[0.2766547323],"iteration":208,"passed_time":0.4691377377,"remaining_time":1.775540433},
{"learn":[0.275663164],"iteration":209,"passed_time":0.4704242538,"remaining_time":1.769691241},
{"learn":[0.2748794956],"iteration":210,"passed_time":0.4718418137,"remaining_time":1.764375313},
{"learn":[0.2742910231],"iteration":211,"passed_time":0.4735113617,"remaining_time":1.760032797},
{"learn":[0.2734098386],"iteration":212,"passed_time":0.474953602,"remaining_time":1.754875515},
{"learn":[0.2729837638],"iteration":213,"passed_time":0.4761752066,"remaining_time":1.748942581},
{"learn":[0.2723968932],"iteration":214,"passed_time":0.4773636308,"remaining_time":1.742932327},
{"learn":[0.2719481667],"iteration":215,"passed_time":0.4786465586,"remaining_time":1.737309731},
{"learn":[0.2713765123],"iteration":216,"passed_time":0.4798078327,"remaining_time":1.73128817},
{"learn":[0.2706812365],"iteration":217,"passed_time":0.4811814966,"remaining_time":1.726073075},
{"learn":[0.2698926769],"iteration":218,"passed_time":0.4823807232,"remaining_time":1.720270981},
{"learn":[0.26950474],"iteration":219,"passed_time":0.483336287,"remaining_time":1.713646836},
{"learn":[0.2689789158],"iteration":220,"passed_time":0.4846270595,"remaining_time":1.708255563},
{"learn":[0.2681493105],"iteration":221,"passed_time":0.486335345,"remaining_time":1.704364407},
{"learn":[0.2675402055],"iteration":222,"passed_time":0.4878197961,"remaining_time":1.699712922},
{"learn":[0.2666760316],"iteration":223,"passed_time":0.4890720228,"remaining_time":1.694285222},
{"learn":[0.2661546776],"iteration":224,"passed_time":0.49026464,"remaining_time":1.688689316},
{"learn":[0.2654144403],"iteration":225,"passed_time":0.4915761261,"remaining_time":1.683539476},
{"learn":[0.2645831661],"iteration":226,"passed_time":0.4928198516,"remaining_time":1.678192711},
{"learn":[0.2639611185],"iteration":227,"passed_time":0.494058971,"remaining_time":1.67286634},
{"learn":[0.2634744947],"iteration":228,"passed_time":0.4952639961,"remaining_time":1.667460878},
{"learn":[0.2627757441],"iteration":229,"passed_time":0.4965315755,"remaining_time":1.662301361},
{"learn":[0.2621212733],"iteration":230,"passed_time":0.4980551013,"remaining_time":1.658027588},
{"learn":[0.2615065203],"iteration":231,"passed_time":0.5000492843,"remaining_time":1.655335562},
{"learn":[0.2606570686],"iteration":232,"passed_time":0.5014608495,"remaining_time":1.650731638},
{"learn":[0.2600106007],"iteration":233,"passed_time":0.5026713163,"remaining_time":1.645496702},
{"learn":[0.2591458292],"iteration":234,"passed_time":0.503912237,"remaining_time":1.640395154},
{"learn":[0.2584617759],"iteration":235,"passed_time":0.5052121859,"remaining_time":1.635517415},
{"learn":[0.2578034987],"iteration":236,"passed_time":0.5064481286,"remaining_time":1.630463806},
{"learn":[0.2570338477],"iteration":237,"passed_time":0.5076870682,"remaining_time":1.625451874},
{"learn":[0.2564660221],"iteration":238,"passed_time":0.5088864426,"remaining_time":1.620345535},
{"learn":[0.2558247718],"iteration":239,"passed_time":0.5101372839,"remaining_time":1.615434732},
{"learn":[0.2553508484],"iteration":240,"passed_time":0.5118377275,"remaining_time":1.61197027},
{"learn":[0.2546999912],"iteration":241,"passed_time":0.5133352064,"remaining_time":1.607884655},
{"learn":[0.2541239304],"iteration":242,"passed_time":0.5146599583,"remaining_time":1.603282257},
{"learn":[0.2535795286],"iteration":243,"passed_time":0.5159999834,"remaining_time":1.598754047},
{"learn":[0.2527853647],"iteration":244,"passed_time":0.5172874254,"remaining_time":1.594089821},
{"learn":[0.2519168234],"iteration":245,"passed_time":0.518713786,"remaining_time":1.58987884},
{"learn":[0.2511660975],"iteration":246,"passed_time":0.5199902051,"remaining_time":1.585233297},
{"learn":[0.2507113438],"iteration":247,"passed_time":0.5211663144,"remaining_time":1.58031076},
{"learn":[0.2502294119],"iteration":248,"passed_time":0.5223613163,"remaining_time":1.575475295},
{"learn":[0.2495620067],"iteration":249,"passed_time":0.5236557602,"remaining_time":1.570967281},
{"learn":[0.2488280291],"iteration":250,"passed_time":0.5253338115,"remaining_time":1.567629581},
{"learn":[0.2487342986],"iteration":251,"passed_time":0.5260642638,"remaining_time":1.561492338},
{"learn":[0.2479310707],"iteration":252,"passed_time":0.5274246608,"remaining_time":1.557257793},
{"learn":[0.2475420979],"iteration":253,"passed_time":0.5287308626,"remaining_time":1.552886707},
{"learn":[0.2471317236],"iteration":254,"passed_time":0.5299709966,"remaining_time":1.548346637},
{"learn":[0.2465951838],"iteration":255,"passed_time":0.5313058258,"remaining_time":1.544107556},
{"learn":[0.2460951695],"iteration":256,"passed_time":0.5326667037,"remaining_time":1.539966384},
{"learn":[0.2454713438],"iteration":257,"passed_time":0.533885309,"remaining_time":1.535437594},
{"learn":[0.2453640294],"iteration":258,"passed_time":0.5346535013,"remaining_time":1.529645731},
{"learn":[0.2449596825],"iteration":259,"passed_time":0.5359194232,"remaining_time":1.525309128},
{"learn":[0.2445755128],"iteration":260,"passed_time":0.537283524,"remaining_time":1.521274039},
{"learn":[0.2437655376],"iteration":261,"passed_time":0.5388834304,"remaining_time":1.517923556},
{"learn":[0.2430828467],"iteration":262,"passed_time":0.5402810471,"remaining_time":1.514019512},
{"learn":[0.2427755563],"iteration":263,"passed_time":0.5415469114,"remaining_time":1.509767147},
{"learn":[0.2421644321],"iteration":264,"passed_time":0.5428859625,"remaining_time":1.505740311},
{"learn":[0.2415896805],"iteration":265,"passed_time":0.544229609,"remaining_time":1.501746365},
{"learn":[0.2412139164],"iteration":266,"passed_time":0.5454837912,"remaining_time":1.497526663},
{"learn":[0.2406088722],"iteration":267,"passed_time":0.5466765673,"remaining_time":1.49316137},
{"learn":[0.2399334678],"iteration":268,"passed_time":0.54785938,"remaining_time":1.48879259},
{"learn":[0.2394101171],"iteration":269,"passed_time":0.5490906396,"remaining_time":1.484578396},
{"learn":[0.23899652],"iteration":270,"passed_time":0.5506636694,"remaining_time":1.48130559},
{"learn":[0.2383976614],"iteration":271,"passed_time":0.5521859121,"remaining_time":1.477909353},
{"learn":[0.2376714517],"iteration":272,"passed_time":0.5535656248,"remaining_time":1.474147287},
{"learn":[0.2368252937],"iteration":273,"passed_time":0.554770947,"remaining_time":1.469940538},
{"learn":[0.2364496107],"iteration":274,"passed_time":0.5560747218,"remaining_time":1.466015176},
{"learn":[0.2358212456],"iteration":275,"passed_time":0.557299475,"remaining_time":1.461901521},
{"learn":[0.2354412586],"iteration":276,"passed_time":0.5585404042,"remaining_time":1.457850947},
{"learn":[0.2349772095],"iteration":277,"passed_time":0.5597424168,"remaining_time":1.453719514},
{"learn":[0.2348666844],"iteration":278,"passed_time":0.5605231213,"remaining_time":1.448520324},
{"learn":[0.2341565212],"iteration":279,"passed_time":0.5617651887,"remaining_time":1.444539057},
{"learn":[0.2335543487],"iteration":280,"passed_time":0.5630600618,"remaining_time":1.4407124},
{"learn":[0.2331268852],"iteration":281,"passed_time":0.5648479515,"remaining_time":1.438158969},
{"learn":[0.23266008],"iteration":282,"passed_time":0.566236717,"remaining_time":1.434599739},
{"learn":[0.2322565601],"iteration":283,"passed_time":0.5675291616,"remaining_time":1.430812957},
{"learn":[0.2316991041],"iteration":284,"passed_time":0.568760662,"remaining_time":1.426890784},
{"learn":[0.231278042],"iteration":285,"passed_time":0.5700399213,"remaining_time":1.423106657},
{"learn":[0.2308042936],"iteration":286,"passed_time":0.5712911376,"remaining_time":1.419270318},
{"learn":[0.2303688508],"iteration":287,"passed_time":0.572485231,"remaining_time":1.41531071},
{"learn":[0.229737066],"iteration":288,"passed_time":0.5736566547,"remaining_time":1.411314469},
{"learn":[0.2293588289],"iteration":289,"passed_time":0.574910479,"remaining_time":1.407539449},
{"learn":[0.2290381265],"iteration":290,"passed_time":0.5761923619,"remaining_time":1.403850119},
{"learn":[0.2285367088],"iteration":291,"passed_time":0.5779714688,"remaining_time":1.401382876},
{"learn":[0.2281041412],"iteration":292,"passed_time":0.5795899199,"remaining_time":1.398532674},
{"learn":[0.2275748054],"iteration":293,"passed_time":0.5809928671,"remaining_time":1.395173348},
{"learn":[0.227150191],"iteration":294,"passed_time":0.5822665231,"remaining_time":1.391518301},
{"learn":[0.2267292427],"iteration":295,"passed_time":0.5835320911,"remaining_time":1.387860108},
{"learn":[0.2263186808],"iteration":296,"passed_time":0.5848962253,"remaining_time":1.384451335},
{"learn":[0.2258016766],"iteration":297,"passed_time":0.5861310363,"remaining_time":1.380751636},
{"learn":[0.2253185549],"iteration":298,"passed_time":0.5874401662,"remaining_time":1.377242664},
{"learn":[0.2247976184],"iteration":299,"passed_time":0.5887185704,"remaining_time":1.373676664},
{"learn":[0.2242937128],"iteration":300,"passed_time":0.5903200107,"remaining_time":1.370876038},
{"learn":[0.2240029238],"iteration":301,"passed_time":0.5920096016,"remaining_time":1.368287092},
{"learn":[0.2236360926],"iteration":302,"passed_time":0.5933894696,"remaining_time":1.364991618},
{"learn":[0.2229558414],"iteration":303,"passed_time":0.5946678863,"remaining_time":1.361476476},
{"learn":[0.2225729513],"iteration":304,"passed_time":0.595937017,"remaining_time":1.357954842},
{"learn":[0.222044303],"iteration":305,"passed_time":0.5971807468,"remaining_time":1.354390321},
{"learn":[0.2214309123],"iteration":306,"passed_time":0.5983906437,"remaining_time":1.350764548},
{"learn":[0.2211721482],"iteration":307,"passed_time":0.5997286905,"remaining_time":1.347442383},
{"learn":[0.2207667425],"iteration":308,"passed_time":0.6009437634,"remaining_time":1.34385806},
{"learn":[0.2205228331],"iteration":309,"passed_time":0.6021489684,"remaining_time":1.340267059},
{"learn":[0.2200474449],"iteration":310,"passed_time":0.6039052557,"remaining_time":1.337912287},
{"learn":[0.2195608242],"iteration":311,"passed_time":0.6055346641,"remaining_time":1.335281567},
{"learn":[0.2192583802],"iteration":312,"passed_time":0.6067735011,"remaining_time":1.331799985},
{"learn":[0.2190764211],"iteration":313,"passed_time":0.6075351719,"remaining_time":1.327290216},
{"learn":[0.2187649395],"iteration":314,"passed_time":0.6087519357,"remaining_time":1.323793892},
{"learn":[0.2184221141],"iteration":315,"passed_time":0.6099589484,"remaining_time":1.320290888},
{"learn":[0.2180497279],"iteration":316,"passed_time":0.6111773023,"remaining_time":1.316826806},
{"learn":[0.2175671396],"iteration":317,"passed_time":0.6123876369,"remaining_time":1.313359649},
{"learn":[0.2172934714],"iteration":318,"passed_time":0.6136470567,"remaining_time":1.310011428},
{"learn":[0.2169704735],"iteration":319,"passed_time":0.6148533147,"remaining_time":1.306563294},
{"learn":[0.2166368886],"iteration":320,"passed_time":0.6162529265,"remaining_time":1.303538122},
{"learn":[0.2161470811],"iteration":321,"passed_time":0.6179220745,"remaining_time":1.301090579},
{"learn":[0.215760351],"iteration":322,"passed_time":0.6193257155,"remaining_time":1.29809136},
{"learn":[0.2152045858],"iteration":323,"passed_time":0.6205596653,"remaining_time":1.294747944},
{"learn":[0.2145616437],"iteration":324,"passed_time":0.6217537523,"remaining_time":1.291334716},
{"learn":[0.2140172751],"iteration":325,"passed_time":0.6229684406,"remaining_time":1.287977696},
{"learn":[0.2134602383],"iteration":326,"passed_time":0.6242053937,"remaining_time":1.284679602},
{"learn":[0.2131788839],"iteration":327,"passed_time":0.6256045731,"remaining_time":1.281726442},
{"learn":[0.2127694447],"iteration":328,"passed_time":0.6268056459,"remaining_time":1.278378688},
{"learn":[0.2122195863],"iteration":329,"passed_time":0.6279957613,"remaining_time":1.275021697},
{"learn":[0.211974927],"iteration":330,"passed_time":0.6294167657,"remaining_time":1.27214446},
{"learn":[0.211483627],"iteration":331,"passed_time":0.6309892495,"remaining_time":1.269580779},
{"learn":[0.2111473412],"iteration":332,"passed_time":0.6323375332,"remaining_time":1.266573978},
{"learn":[0.2107119533],"iteration":333,"passed_time":0.6336675087,"remaining_time":1.263540601},
{"learn":[0.2103218628],"iteration":334,"passed_time":0.634917864,"remaining_time":1.260359342},
{"learn":[0.2101198323],"iteration":335,"passed_time":0.6361586693,"remaining_time":1.257170704},
{"learn":[0.2098186223],"iteration":336,"passed_time":0.6373981309,"remaining_time":1.253990982},
{"learn":[0.2095333096],"iteration":337,"passed_time":0.6386467885,"remaining_time":1.250840751},
{"learn":[0.2091540826],"iteration":338,"passed_time":0.6398884677,"remaining_time":1.247688133},
{"learn":[0.2086231701],"iteration":339,"passed_time":0.6411571012,"remaining_time":1.244599079},
{"learn":[0.2080506282],"iteration":340,"passed_time":0.6430066556,"remaining_time":1.242643361},
{"learn":[0.2078282546],"iteration":341,"passed_time":0.6446875805,"remaining_time":1.240363824},
{"learn":[0.2073326799],"iteration":342,"passed_time":0.6460509483,"remaining_time":1.237479513},
{"learn":[0.2069940764],"iteration":343,"passed_time":0.6473135327,"remaining_time":1.234411853},
{"learn":[0.2065715636],"iteration":344,"passed_time":0.6485132921,"remaining_time":1.231235381},
{"learn":[0.2061550829],"iteration":345,"passed_time":0.6497378508,"remaining_time":1.228117209},
{"learn":[0.2057688358],"iteration":346,"passed_time":0.650994866,"remaining_time":1.22507103},
{"learn":[0.2053509941],"iteration":347,"passed_time":0.6522052729,"remaining_time":1.22194781},
{"learn":[0.2050547069],"iteration":348,"passed_time":0.6534236834,"remaining_time":1.218850481},
{"learn":[0.2045884383],"iteration":349,"passed_time":0.6547483299,"remaining_time":1.215961184},
{"learn":[0.2044482822],"iteration":350,"passed_time":0.6564926516,"remaining_time":1.213856783},
{"learn":[0.2041276857],"iteration":351,"passed_time":0.6580868204,"remaining_time":1.21147801},
{"learn":[0.203853087],"iteration":352,"passed_time":0.6593586128,"remaining_time":1.208512812},
{"learn":[0.2035507626],"iteration":353,"passed_time":0.6605463101,"remaining_time":1.205403718},
{"learn":[0.2031758414],"iteration":354,"passed_time":0.6617852116,"remaining_time":1.202398483},
{"learn":[0.2029434176],"iteration":355,"passed_time":0.662953069,"remaining_time":1.199274653},
{"learn":[0.2025650928],"iteration":356,"passed_time":0.6641794664,"remaining_time":1.196267218},
{"learn":[0.2022287679],"iteration":357,"passed_time":0.6654182795,"remaining_time":1.193291999},
{"learn":[0.2018708607],"iteration":358,"passed_time":0.6665989149,"remaining_time":1.190222575},
{"learn":[0.2015739148],"iteration":359,"passed_time":0.6679813936,"remaining_time":1.187522478},
{"learn":[0.2011872182],"iteration":360,"passed_time":0.6696940189,"remaining_time":1.185414067},
{"learn":[0.200891489],"iteration":361,"passed_time":0.6712251025,"remaining_time":1.182987888},
{"learn":[0.200565267],"iteration":362,"passed_time":0.672498231,"remaining_time":1.180113976},
{"learn":[0.2002502844],"iteration":363,"passed_time":0.6736974252,"remaining_time":1.177119677},
{"learn":[0.199742204],"iteration":364,"passed_time":0.6749120006,"remaining_time":1.174161974},
{"learn":[0.1992548498],"iteration":365,"passed_time":0.6761315714,"remaining_time":1.171222449},
{"learn":[0.1988368027],"iteration":366,"passed_time":0.677357788,"remaining_time":1.16830376},
{"learn":[0.1984071276],"iteration":367,"passed_time":0.6785481085,"remaining_time":1.165332621},
{"learn":[0.1979968888],"iteration":368,"passed_time":0.6797442767,"remaining_time":1.162381134},
{"learn":[0.1978232159],"iteration":369,"passed_time":0.681041189,"remaining_time":1.159610673},
{"learn":[0.1975593149],"iteration":370,"passed_time":0.6829584932,"remaining_time":1.157899979},
{"learn":[0.1972737649],"iteration":371,"passed_time":0.6845180973,"remaining_time":1.155584315},
{"learn":[0.1968894548],"iteration":372,"passed_time":0.6857903683,"remaining_time":1.152789708},
{"learn":[0.1963816087],"iteration":373,"passed_time":0.6870038503,"remaining_time":1.14990484},
{"learn":[0.1958916485],"iteration":374,"passed_time":0.6882252762,"remaining_time":1.147042127},
{"learn":[0.1955212773],"iteration":375,"passed_time":0.6894761389,"remaining_time":1.144236997},
{"learn":[0.1951830358],"iteration":376,"passed_time":0.6907246188,"remaining_time":1.141436174},
{"learn":[0.1948283525],"iteration":377,"passed_time":0.6919366671,"remaining_time":1.138583616},
{"learn":[0.1946702998],"iteration":378,"passed_time":0.6932354547,"remaining_time":1.13588184},
{"learn":[0.1945567319],"iteration":379,"passed_time":0.6945671404,"remaining_time":1.133241124},
{"learn":[0.1942883649],"iteration":380,"passed_time":0.6964099835,"remaining_time":1.131437742},
{"learn":[0.1938961661],"iteration":381,"passed_time":0.6978071408,"remaining_time":1.128913123},
{"learn":[0.1936205848],"iteration":382,"passed_time":0.6990850963,"remaining_time":1.126202361},
{"learn":[0.1932172516],"iteration":383,"passed_time":0.700369095,"remaining_time":1.123508757},
{"learn":[0.1927948469],"iteration":384,"passed_time":0.7015789239,"remaining_time":1.120703995},
{"learn":[0.192432682],"iteration":385,"passed_time":0.7028026048,"remaining_time":1.117929532},
{"learn":[0.192145981],"iteration":386,"passed_time":0.7039627432,"remaining_time":1.115062433},
{"learn":[0.191830172],"iteration":387,"passed_time":0.7051484416,"remaining_time":1.112244449},
{"learn":[0.1916051661],"iteration":388,"passed_time":0.7064369641,"remaining_time":1.109596363},
{"learn":[0.1912456982],"iteration":389,"passed_time":0.7076569961,"remaining_time":1.106848122},
{"learn":[0.1910158284],"iteration":390,"passed_time":0.7093827058,"remaining_time":1.104895314},
{"learn":[0.1908632162],"iteration":391,"passed_time":0.7109361945,"remaining_time":1.102676547},
{"learn":[0.1903827292],"iteration":392,"passed_time":0.7121881808,"remaining_time":1.099995485},
{"learn":[0.1899427723],"iteration":393,"passed_time":0.7134348679,"remaining_time":1.097313528},
{"learn":[0.1897277248],"iteration":394,"passed_time":0.7146491566,"remaining_time":1.094589215},
{"learn":[0.1891535304],"iteration":395,"passed_time":0.7159034061,"remaining_time":1.091933478},
{"learn":[0.1889188513],"iteration":396,"passed_time":0.7171935028,"remaining_time":1.08933925},
{"learn":[0.1886078862],"iteration":397,"passed_time":0.7184803024,"remaining_time":1.086746588},
{"learn":[0.1881241663],"iteration":398,"passed_time":0.7197403525,"remaining_time":1.08412018},
{"learn":[0.1879382832],"iteration":399,"passed_time":0.7209603553,"remaining_time":1.081440533},
{"learn":[0.1876673638],"iteration":400,"passed_time":0.7226906452,"remaining_time":1.079530415},
{"learn":[0.1874537535],"iteration":401,"passed_time":0.7241761333,"remaining_time":1.077257034},
{"learn":[0.187260328],"iteration":402,"passed_time":0.7254812554,"remaining_time":1.074720371},
{"learn":[0.1870463839],"iteration":403,"passed_time":0.7267526151,"remaining_time":1.072139996},
{"learn":[0.1869163858],"iteration":404,"passed_time":0.7279989272,"remaining_time":1.069529288},
{"learn":[0.1866660784],"iteration":405,"passed_time":0.7292653484,"remaining_time":1.066954722},
{"learn":[0.1864937484],"iteration":406,"passed_time":0.7304484457,"remaining_time":1.06426518},
{"learn":[0.1860902331],"iteration":407,"passed_time":0.7317314055,"remaining_time":1.061727922},
{"learn":[0.1857598196],"iteration":408,"passed_time":0.7329311667,"remaining_time":1.059076576},
{"learn":[0.1854399131],"iteration":409,"passed_time":0.734139929,"remaining_time":1.056445264},
{"learn":[0.1851926823],"iteration":410,"passed_time":0.7359304387,"remaining_time":1.05465457},
{"learn":[0.1848511621],"iteration":411,"passed_time":0.7374820663,"remaining_time":1.052522949},
{"learn":[0.1843920859],"iteration":412,"passed_time":0.7387818614,"remaining_time":1.050036205},
{"learn":[0.1840676287],"iteration":413,"passed_time":0.7401234823,"remaining_time":1.047614398},
{"learn":[0.1837482729],"iteration":414,"passed_time":0.7413841011,"remaining_time":1.045083612},
{"learn":[0.1836036918],"iteration":415,"passed_time":0.7427459234,"remaining_time":1.042701008},
{"learn":[0.1832133349],"iteration":416,"passed_time":0.7440204266,"remaining_time":1.04020122},
{"learn":[0.1829337087],"iteration":417,"passed_time":0.7453053551,"remaining_time":1.03772181},
{"learn":[0.1825108304],"iteration":418,"passed_time":0.7465070422,"remaining_time":1.035132677},
{"learn":[0.1821880504],"iteration":419,"passed_time":0.7479385093,"remaining_time":1.032867465},
{"learn":[0.1818802156],"iteration":420,"passed_time":0.7497368524,"remaining_time":1.031110778},
{"learn":[0.1816860843],"iteration":421,"passed_time":0.7512751366,"remaining_time":1.028997699},
{"learn":[0.1812041698],"iteration":422,"passed_time":0.7525995786,"remaining_time":1.026595643},
{"learn":[0.1808299941],"iteration":423,"passed_time":0.7538498986,"remaining_time":1.024097975},
{"learn":[0.1806744598],"iteration":424,"passed_time":0.7551633284,"remaining_time":1.021691562},
{"learn":[0.1805198076],"iteration":425,"passed_time":0.7563725291,"remaining_time":1.01914984},
{"learn":[0.1800983964],"iteration":426,"passed_time":0.7576208722,"remaining_time":1.016666885},
{"learn":[0.1799154039],"iteration":427,"passed_time":0.758774539,"remaining_time":1.014063169},
{"learn":[0.1795296279],"iteration":428,"passed_time":0.7599983716,"remaining_time":1.011559604},
{"learn":[0.1792637231],"iteration":429,"passed_time":0.7614097145,"remaining_time":1.009310552},
{"learn":[0.1790004085],"iteration":430,"passed_time":0.763370445,"remaining_time":1.00779068},
{"learn":[0.1787872646],"iteration":431,"passed_time":0.7650453908,"remaining_time":1.005893014},
{"learn":[0.1786196215],"iteration":432,"passed_time":0.7663597647,"remaining_time":1.003524218},
{"learn":[0.1784881084],"iteration":433,"passed_time":0.7676066851,"remaining_time":1.001072313},
{"learn":[0.1782911993],"iteration":434,"passed_time":0.7688558099,"remaining_time":0.9986288106},
{"learn":[0.1781546154],"iteration":435,"passed_time":0.7694871923,"remaining_time":0.9953916892},
{"learn":[0.1778293091],"iteration":436,"passed_time":0.7707647878,"remaining_time":0.9929990287},
{"learn":[0.1775703789],"iteration":437,"passed_time":0.7719223998,"remaining_time":0.9904575084},
{"learn":[0.1773578167],"iteration":438,"passed_time":0.7731531723,"remaining_time":0.9880157851},
{"learn":[0.1770480144],"iteration":439,"passed_time":0.774575146,"remaining_time":0.9858229131},
{"learn":[0.1768409076],"iteration":440,"passed_time":0.7761870821,"remaining_time":0.9838743285},
{"learn":[0.1764859737],"iteration":441,"passed_time":0.7775908246,"remaining_time":0.9816644346},
{"learn":[0.1762924443],"iteration":442,"passed_time":0.7788066995,"remaining_time":0.9792219675},
{"learn":[0.1760704084],"iteration":443,"passed_time":0.7800521668,"remaining_time":0.9768220828},
{"learn":[0.1759194242],"iteration":444,"passed_time":0.7812618384,"remaining_time":0.9743827422},
{"learn":[0.1755985593],"iteration":445,"passed_time":0.7824981504,"remaining_time":0.9719820074},
{"learn":[0.1753594434],"iteration":446,"passed_time":0.7837291362,"remaining_time":0.9695798933},
{"learn":[0.1751844932],"iteration":447,"passed_time":0.7849311043,"remaining_time":0.9671472535},
{"learn":[0.1747174959],"iteration":448,"passed_time":0.7861338274,"remaining_time":0.964721022},
{"learn":[0.174533139],"iteration":449,"passed_time":0.7948291088,"remaining_time":0.9714577997},
{"learn":[0.1742804266],"iteration":450,"passed_time":0.7964746107,"remaining_time":0.9695444817},
{"learn":[0.1739557771],"iteration":451,"passed_time":0.7977751155,"remaining_time":0.9672140781},
{"learn":[0.1737755613],"iteration":452,"passed_time":0.7990657282,"remaining_time":0.9648762766},
{"learn":[0.1733882488],"iteration":453,"passed_time":0.8003078697,"remaining_time":0.9624847948},
{"learn":[0.1730708046],"iteration":454,"passed_time":0.8016623475,"remaining_time":0.9602329218},
{"learn":[0.1727858923],"iteration":455,"passed_time":0.8034101472,"remaining_time":0.9584542107},
{"learn":[0.1723525942],"iteration":456,"passed_time":0.8050034453,"remaining_time":0.9564920586},
{"learn":[0.1720139752],"iteration":457,"passed_time":0.8063399408,"remaining_time":0.9542276155},
{"learn":[0.171633101],"iteration":458,"passed_time":0.807577365,"remaining_time":0.9518504455},
{"learn":[0.1713431897],"iteration":459,"passed_time":0.8087847135,"remaining_time":0.9494429246},
{"learn":[0.1711271511],"iteration":460,"passed_time":0.8099829946,"remaining_time":0.9470300089},
{"learn":[0.1707877359],"iteration":461,"passed_time":0.8112120484,"remaining_time":0.9446581862},
{"learn":[0.1704401729],"iteration":462,"passed_time":0.8125229714,"remaining_time":0.9423862541},
{"learn":[0.1703447864],"iteration":463,"passed_time":0.8137730589,"remaining_time":0.9400481887},
{"learn":[0.1701093628],"iteration":464,"passed_time":0.8151737835,"remaining_time":0.9378881165},
{"learn":[0.1697908873],"iteration":465,"passed_time":0.8167840803,"remaining_time":0.9359714568},
{"learn":[0.1696858841],"iteration":466,"passed_time":0.8181435749,"remaining_time":0.9337698617},
{"learn":[0.1694219757],"iteration":467,"passed_time":0.8195454317,"remaining_time":0.9316200207},
{"learn":[0.1691895261],"iteration":468,"passed_time":0.8209334974,"remaining_time":0.9294577551},
{"learn":[0.1689464692],"iteration":469,"passed_time":0.8222273334,"remaining_time":0.9271925249},
{"learn":[0.1686755258],"iteration":470,"passed_time":0.8234832414,"remaining_time":0.924888821},
{"learn":[0.1683614528],"iteration":471,"passed_time":0.824757277,"remaining_time":0.9226098353},
{"learn":[0.1680276154],"iteration":472,"passed_time":0.8260512526,"remaining_time":0.9203573153},
{"learn":[0.167579349],"iteration":473,"passed_time":0.8272572026,"remaining_time":0.9180111573},
{"learn":[0.167466176],"iteration":474,"passed_time":0.8289162106,"remaining_time":0.9161705486},
{"learn":[0.1672345231],"iteration":475,"passed_time":0.8305416318,"remaining_time":0.9142937291},
{"learn":[0.1671930021],"iteration":476,"passed_time":0.8319132027,"remaining_time":0.9121396332},
{"learn":[0.1670708413],"iteration":477,"passed_time":0.8328316985,"remaining_time":0.9094940306},
{"learn":[0.166940002],"iteration":478,"passed_time":0.834296616,"remaining_time":0.9074499727},
{"learn":[0.1667369367],"iteration":479,"passed_time":0.8354753624,"remaining_time":0.9050983093},
{"learn":[0.1665908749],"iteration":480,"passed_time":0.8367332907,"remaining_time":0.9028369602},
{"learn":[0.1664949382],"iteration":481,"passed_time":0.8379702228,"remaining_time":0.9005572104},
{"learn":[0.1662035873],"iteration":482,"passed_time":0.8392977171,"remaining_time":0.8983787159},
{"learn":[0.1659495133],"iteration":483,"passed_time":0.840506675,"remaining_time":0.8960773642},
{"learn":[0.1656792071],"iteration":484,"passed_time":0.8422610171,"remaining_time":0.8943596367},
{"learn":[0.1653579948],"iteration":485,"passed_time":0.8438897278,"remaining_time":0.8925088891},
{"learn":[0.1650360982],"iteration":486,"passed_time":0.845299105,"remaining_time":0.8904280099},
{"learn":[0.164789887],"iteration":487,"passed_time":0.8466210701,"remaining_time":0.8882581719},
{"learn":[0.1645073398],"iteration":488,"passed_time":0.8478129501,"remaining_time":0.8859558641},
{"learn":[0.1643900725],"iteration":489,"passed_time":0.8490309337,"remaining_time":0.8836852575},
{"learn":[0.1642203673],"iteration":490,"passed_time":0.8502305855,"remaining_time":0.8813999349},
{"learn":[0.1639009966],"iteration":491,"passed_time":0.8515262478,"remaining_time":0.8792181583},
{"learn":[0.1636702479],"iteration":492,"passed_time":0.8527060301,"remaining_time":0.8769208058},
{"learn":[0.1635780263],"iteration":493,"passed_time":0.8534583469,"remaining_time":0.8741901286},
{"learn":[0.163381857],"iteration":494,"passed_time":0.8548375419,"remaining_time":0.8721069871},
{"learn":[0.1629572133],"iteration":495,"passed_time":0.8564278837,"remaining_time":0.8702412367},
{"learn":[0.1628421865],"iteration":496,"passed_time":0.8578560089,"remaining_time":0.8682124194},
{"learn":[0.1626300422],"iteration":497,"passed_time":0.8590927233,"remaining_time":0.8659930665},
{"learn":[0.1624625139],"iteration":498,"passed_time":0.8603169366,"remaining_time":0.8637651007},
{"learn":[0.162336889],"iteration":499,"passed_time":0.8615498747,"remaining_time":0.8615498747},
{"learn":[0.1620728909],"iteration":500,"passed_time":0.8628116079,"remaining_time":0.8593672502},
{"learn":[0.1617623922],"iteration":501,"passed_time":0.86404226,"remaining_time":0.8571574611},
{"learn":[0.16154666],"iteration":502,"passed_time":0.8652750627,"remaining_time":0.8549536902},
{"learn":[0.1614166398],"iteration":503,"passed_time":0.8664436898,"remaining_time":0.8526906153},
{"learn":[0.1612027965],"iteration":504,"passed_time":0.8678380732,"remaining_time":0.8506531608},
{"learn":[0.1610846974],"iteration":505,"passed_time":0.8694346473,"remaining_time":0.8488156438},
{"learn":[0.1609204245],"iteration":506,"passed_time":0.8708784951,"remaining_time":0.8468305683},
{"learn":[0.1607098013],"iteration":507,"passed_time":0.8721207941,"remaining_time":0.8446524226},
{"learn":[0.160494477],"iteration":508,"passed_time":0.873331837,"remaining_time":0.8424478035},
{"learn":[0.1602163851],"iteration":509,"passed_time":0.8745201401,"remaining_time":0.8402252327},
{"learn":[0.159990975],"iteration":510,"passed_time":0.8757940938,"remaining_time":0.838088673},
{"learn":[0.1597996736],"iteration":511,"passed_time":0.8770477675,"remaining_time":0.8359361534},
{"learn":[0.1595406822],"iteration":512,"passed_time":0.8783623337,"remaining_time":0.8338449445},
{"learn":[0.1594274615],"iteration":513,"passed_time":0.8796086853,"remaining_time":0.8316922589},
{"learn":[0.1592842971],"iteration":514,"passed_time":0.8813022,"remaining_time":0.8299642078},
{"learn":[0.1591075707],"iteration":515,"passed_time":0.8828058218,"remaining_time":0.828058174},
{"learn":[0.1590026417],"iteration":516,"passed_time":0.884130329,"remaining_time":0.8259863615},
{"learn":[0.1588203167],"iteration":517,"passed_time":0.8854105168,"remaining_time":0.8238761951},
{"learn":[0.1584899674],"iteration":518,"passed_time":0.8875023401,"remaining_time":0.8225214366},
{"learn":[0.1581888964],"iteration":519,"passed_time":0.8895854056,"remaining_time":0.821155759},
{"learn":[0.1580661903],"iteration":520,"passed_time":0.8917695124,"remaining_time":0.8198802235},
{"learn":[0.1577629116],"iteration":521,"passed_time":0.8941269746,"remaining_time":0.81875995},
{"learn":[0.1573792554],"iteration":522,"passed_time":0.896164263,"remaining_time":0.8173429321},
{"learn":[0.1570397458],"iteration":523,"passed_time":0.898160153,"remaining_time":0.8158859405},
{"learn":[0.1569608193],"iteration":524,"passed_time":0.9001486846,"remaining_time":0.8144202384},
{"learn":[0.1567547855],"iteration":525,"passed_time":0.9028238116,"remaining_time":0.8135712675},
{"learn":[0.1566123676],"iteration":526,"passed_time":0.90467662,"remaining_time":0.8119773079},
{"learn":[0.1561312263],"iteration":527,"passed_time":0.9060848821,"remaining_time":0.8099849703},
{"learn":[0.1558788802],"iteration":528,"passed_time":0.9074817434,"remaining_time":0.8079846903},
{"learn":[0.1556116907],"iteration":529,"passed_time":0.9091269664,"remaining_time":0.8062069325},
{"learn":[0.1552429709],"iteration":530,"passed_time":0.9115154659,"remaining_time":0.8050861648},
{"learn":[0.1549791544],"iteration":531,"passed_time":0.9136453765,"remaining_time":0.8037331507},
{"learn":[0.1548762838],"iteration":532,"passed_time":0.9153876291,"remaining_time":0.8020375662},
{"learn":[0.1546143437],"iteration":533,"passed_time":0.9178781895,"remaining_time":0.8009948246},
{"learn":[0.1544828824],"iteration":534,"passed_time":0.9194562375,"remaining_time":0.7991535522},
{"learn":[0.1541765321],"iteration":535,"passed_time":0.9208383064,"remaining_time":0.7971436085},
{"learn":[0.1539028083],"iteration":536,"passed_time":0.9220953404,"remaining_time":0.7950281986},
{"learn":[0.1537993523],"iteration":537,"passed_time":0.9233715627,"remaining_time":0.7929324572},
{"learn":[0.1534792859],"iteration":538,"passed_time":0.9246211013,"remaining_time":0.7908169345},
{"learn":[0.153140965],"iteration":539,"passed_time":0.9258496583,"remaining_time":0.788686746},
{"learn":[0.1530630303],"iteration":540,"passed_time":0.9271086796,"remaining_time":0.7865857374},
{"learn":[0.1528100217],"iteration":541,"passed_time":0.9283166801,"remaining_time":0.7844447223},
{"learn":[0.1525307777],"iteration":542,"passed_time":0.9296594553,"remaining_time":0.7824205728},
{"learn":[0.1523386183],"iteration":543,"passed_time":0.931350846,"remaining_time":0.7806911503},
{"learn":[0.1520258443],"iteration":544,"passed_time":0.9328131968,"remaining_time":0.7787706506},
{"learn":[0.1519383702],"iteration":545,"passed_time":0.9340567682,"remaining_time":0.7766699135},
{"learn":[0.1517234341],"iteration":546,"passed_time":0.9352891999,"remaining_time":0.7745630851},
{"learn":[0.1514546111],"iteration":547,"passed_time":0.9364936395,"remaining_time":0.7724363596},
{"learn":[0.1510916164],"iteration":548,"passed_time":0.9378123681,"remaining_time":0.7704068816},
{"learn":[0.1507858532],"iteration":549,"passed_time":0.9390758837,"remaining_time":0.768334814},
{"learn":[0.150453677],"iteration":550,"passed_time":0.9402931023,"remaining_time":0.7662279545},
{"learn":[0.1502142811],"iteration":551,"passed_time":0.9414424685,"remaining_time":0.7640692498},
{"learn":[0.1500512708],"iteration":552,"passed_time":0.9427623823,"remaining_time":0.7620520523},
{"learn":[0.1500058232],"iteration":553,"passed_time":0.9443835279,"remaining_time":0.7602798798},
{"learn":[0.1499227898],"iteration":554,"passed_time":0.9457233521,"remaining_time":0.7582826877},
{"learn":[0.1498088439],"iteration":555,"passed_time":0.9469725752,"remaining_time":0.7562155097},
{"learn":[0.1495173413],"iteration":556,"passed_time":0.9482085568,"remaining_time":0.7541407372},
{"learn":[0.1492262366],"iteration":557,"passed_time":0.9494362843,"remaining_time":0.7520624331},
{"learn":[0.1490325321],"iteration":558,"passed_time":0.9506791634,"remaining_time":0.7499991253},
{"learn":[0.1488594427],"iteration":559,"passed_time":0.9518976975,"remaining_time":0.7479196194},
{"learn":[0.1487148897],"iteration":560,"passed_time":0.9531403358,"remaining_time":0.7458620453},
{"learn":[0.1484010276],"iteration":561,"passed_time":0.9543450543,"remaining_time":0.7437778181},
{"learn":[0.1482146916],"iteration":562,"passed_time":0.9556303749,"remaining_time":0.7417592785},
{"learn":[0.147950774],"iteration":563,"passed_time":0.9573116808,"remaining_time":0.7400494554},
{"learn":[0.1478228231],"iteration":564,"passed_time":0.95874641,"remaining_time":0.7381498909},
{"learn":[0.1475831377],"iteration":565,"passed_time":0.9600295739,"remaining_time":0.736135751},
{"learn":[0.1474648108],"iteration":566,"passed_time":0.9612398775,"remaining_time":0.7340685484},
{"learn":[0.1471904009],"iteration":567,"passed_time":0.9624602788,"remaining_time":0.732012043},
{"learn":[0.1471204942],"iteration":568,"passed_time":0.9636549876,"remaining_time":0.7299390152},
{"learn":[0.1469332201],"iteration":569,"passed_time":0.9648906483,"remaining_time":0.7278999627},
{"learn":[0.1466709288],"iteration":570,"passed_time":0.9660858916,"remaining_time":0.7258333581},
{"learn":[0.146480304],"iteration":571,"passed_time":0.9673010984,"remaining_time":0.723784738},
{"learn":[0.1463778598],"iteration":572,"passed_time":0.9685556378,"remaining_time":0.7217683374},
{"learn":[0.1462250236],"iteration":573,"passed_time":0.9703576484,"remaining_time":0.7201609028},
{"learn":[0.1460796567],"iteration":574,"passed_time":0.9719233337,"remaining_time":0.7183781162},
{"learn":[0.145894389],"iteration":575,"passed_time":0.9731294464,"remaining_time":0.7163313981},
{"learn":[0.1458031621],"iteration":576,"passed_time":0.9742840897,"remaining_time":0.7142498613},
{"learn":[0.1455868408],"iteration":577,"passed_time":0.975537826,"remaining_time":0.7122438799},
{"learn":[0.145390599],"iteration":578,"passed_time":0.9767779718,"remaining_time":0.7102306151},
{"learn":[0.1452052232],"iteration":579,"passed_time":0.9779385557,"remaining_time":0.7081624024},
{"learn":[0.145028504],"iteration":580,"passed_time":0.9792653983,"remaining_time":0.706217215},
{"learn":[0.1448788858],"iteration":581,"passed_time":0.9804572168,"remaining_time":0.7041771763},
{"learn":[0.1445805931],"iteration":582,"passed_time":0.9816429885,"remaining_time":0.7021357225},
{"learn":[0.1443785009],"iteration":583,"passed_time":0.9832057999,"remaining_time":0.7003657753},
{"learn":[0.1442216908],"iteration":584,"passed_time":0.9848168442,"remaining_time":0.6986307528},
{"learn":[0.1439444719],"iteration":585,"passed_time":0.9860862751,"remaining_time":0.6966548087},
{"learn":[0.1437395908],"iteration":586,"passed_time":0.9873110579,"remaining_time":0.6946498584},
{"learn":[0.1436102564],"iteration":587,"passed_time":0.9885478147,"remaining_time":0.6926559518},
{"learn":[0.143475395],"iteration":588,"passed_time":0.9899294178,"remaining_time":0.6907656888},
{"learn":[0.1432972723],"iteration":589,"passed_time":0.9912139723,"remaining_time":0.6888097096},
{"learn":[0.1430575045],"iteration":590,"passed_time":0.9924077456,"remaining_time":0.6867931776},
{"learn":[0.1429191924],"iteration":591,"passed_time":0.9937538277,"remaining_time":0.6848843948},
{"learn":[0.1427825344],"iteration":592,"passed_time":0.994986206,"remaining_time":0.6828994702},
{"learn":[0.142670877],"iteration":593,"passed_time":0.9968132302,"remaining_time":0.681323521},
{"learn":[0.1424974691],"iteration":594,"passed_time":0.9984018926,"remaining_time":0.6795844815},
{"learn":[0.1424580173],"iteration":595,"passed_time":0.9998021668,"remaining_time":0.6777182473},
{"learn":[0.1422924884],"iteration":596,"passed_time":1.001121412,"remaining_time":0.675798876},
{"learn":[0.1418955352],"iteration":597,"passed_time":1.002339948,"remaining_time":0.6738138112},
{"learn":[0.1417618666],"iteration":598,"passed_time":1.003558604,"remaining_time":0.6718313862},
{"learn":[0.1414807283],"iteration":599,"passed_time":1.00478028,"remaining_time":0.6698535201},
{"learn":[0.1412489704],"iteration":600,"passed_time":1.006028694,"remaining_time":0.6678959218},
{"learn":[0.1411041963],"iteration":601,"passed_time":1.007245361,"remaining_time":0.6659196908},
{"learn":[0.1408737242],"iteration":602,"passed_time":1.00846688,"remaining_time":0.663949173},
{"learn":[0.1406671952],"iteration":603,"passed_time":1.010570536,"remaining_time":0.6625594905},
{"learn":[0.1405776071],"iteration":604,"passed_time":1.012031657,"remaining_time":0.6607479414},
{"learn":[0.1405745035],"iteration":605,"passed_time":1.012659741,"remaining_time":0.6583959375},
{"learn":[0.1404479035],"iteration":606,"passed_time":1.013959303,"remaining_time":0.6564843592},
{"learn":[0.1403390497],"iteration":607,"passed_time":1.015165198,"remaining_time":0.6545144038},
{"learn":[0.1403068144],"iteration":608,"passed_time":1.016411504,"remaining_time":0.6525729031},
{"learn":[0.140032502],"iteration":609,"passed_time":1.017614871,"remaining_time":0.6506062293},
{"learn":[0.1397896686],"iteration":610,"passed_time":1.018834336,"remaining_time":0.6486523024},
{"learn":[0.1397472227],"iteration":611,"passed_time":1.020033205,"remaining_time":0.6466877181},
{"learn":[0.1395304425],"iteration":612,"passed_time":1.021356926,"remaining_time":0.6448044541},
{"learn":[0.1394271003],"iteration":613,"passed_time":1.023139259,"remaining_time":0.6432113255},
{"learn":[0.139294495],"iteration":614,"passed_time":1.024718958,"remaining_time":0.6414907301},
{"learn":[0.139108227],"iteration":615,"passed_time":1.026085189,"remaining_time":0.6396375206},
{"learn":[0.1389080852],"iteration":616,"passed_time":1.02753192,"remaining_time":0.6378358593},
{"learn":[0.1387349436],"iteration":617,"passed_time":1.028892836,"remaining_time":0.6359823029},
{"learn":[0.1385751758],"iteration":618,"passed_time":1.030192125,"remaining_time":0.6340924064},
{"learn":[0.1384343022],"iteration":619,"passed_time":1.031513474,"remaining_time":0.6322179359},
{"learn":[0.1383076402],"iteration":620,"passed_time":1.032750235,"remaining_time":0.6302936219},
{"learn":[0.1382895736],"iteration":621,"passed_time":1.033977926,"remaining_time":0.6283660064},
{"learn":[0.1380464983],"iteration":622,"passed_time":1.035302372,"remaining_time":0.6264991883},
{"learn":[0.1379092765],"iteration":623,"passed_time":1.037241139,"remaining_time":0.6250042762},
{"learn":[0.1376666575],"iteration":624,"passed_time":1.038698039,"remaining_time":0.6232188233},
{"learn":[0.1375659702],"iteration":625,"passed_time":1.039919689,"remaining_time":0.6212938717},
{"learn":[0.1373561181],"iteration":626,"passed_time":1.041110225,"remaining_time":0.6193526538},
{"learn":[0.1371627653],"iteration":627,"passed_time":1.042326936,"remaining_time":0.6174293314},
{"learn":[0.1370095556],"iteration":628,"passed_time":1.043518399,"remaining_time":0.6154933642},
{"learn":[0.1369024891],"iteration":629,"passed_time":1.044705806,"remaining_time":0.6135573783},
{"learn":[0.1366855612],"iteration":630,"passed_time":1.045923527,"remaining_time":0.6116414918},
{"learn":[0.1365118259],"iteration":631,"passed_time":1.047075287,"remaining_time":0.6096894075},
{"learn":[0.1363240351],"iteration":632,"passed_time":1.048413618,"remaining_time":0.6078480219},
{"learn":[0.1361600322],"iteration":633,"passed_time":1.050212483,"remaining_time":0.606274083},
{"learn":[0.1360851168],"iteration":634,"passed_time":1.051870361,"remaining_time":0.6046183967},
{"learn":[0.1359695011],"iteration":635,"passed_time":1.053230057,"remaining_time":0.6027920453},
{"learn":[0.1358215707],"iteration":636,"passed_time":1.054492729,"remaining_time":0.600911869},
{"learn":[0.1356592534],"iteration":637,"passed_time":1.055672928,"remaining_time":0.5989868338},
{"learn":[0.1355120883],"iteration":638,"passed_time":1.056852975,"remaining_time":0.5970640437},
{"learn":[0.1353077982],"iteration":639,"passed_time":1.058071127,"remaining_time":0.5951650092},
{"learn":[0.1351866826],"iteration":640,"passed_time":1.059029802,"remaining_time":0.5931227752},
{"learn":[0.1350508963],"iteration":641,"passed_time":1.06023335,"remaining_time":0.5912204663},
{"learn":[0.1349672984],"iteration":642,"passed_time":1.06146495,"remaining_time":0.5893359056},
{"learn":[0.134837094],"iteration":643,"passed_time":1.063295223,"remaining_time":0.587784316},
{"learn":[0.1347057776],"iteration":644,"passed_time":1.064866571,"remaining_time":0.586089353},
{"learn":[0.1345463234],"iteration":645,"passed_time":1.066112014,"remaining_time":0.5842161812},
{"learn":[0.1343943744],"iteration":646,"passed_time":1.067350248,"remaining_time":0.5823410164},
{"learn":[0.1343914272],"iteration":647,"passed_time":1.067942648,"remaining_time":0.5801169941},
{"learn":[0.1342377934],"iteration":648,"passed_time":1.069088643,"remaining_time":0.5781974015},
{"learn":[0.1339452185],"iteration":649,"passed_time":1.070442522,"remaining_time":0.5763921275},
{"learn":[0.1337408638],"iteration":650,"passed_time":1.071671373,"remaining_time":0.574521212},
{"learn":[0.1336740791],"iteration":651,"passed_time":1.072945257,"remaining_time":0.5726763029},
{"learn":[0.1335150094],"iteration":652,"passed_time":1.074169002,"remaining_time":0.5708064987},
{"learn":[0.1333270678],"iteration":653,"passed_time":1.07613643,"remaining_time":0.5693321174},
{"learn":[0.1330354216],"iteration":654,"passed_time":1.077783433,"remaining_time":0.5676874572},
{"learn":[0.1329105661],"iteration":655,"passed_time":1.079128375,"remaining_time":0.565884392},
{"learn":[0.1328108705],"iteration":656,"passed_time":1.080547656,"remaining_time":0.5641215313},
{"learn":[0.1326689903],"iteration":657,"passed_time":1.081819093,"remaining_time":0.5622828723},
{"learn":[0.1324350667],"iteration":658,"passed_time":1.083139344,"remaining_time":0.5604711931},
{"learn":[0.1322739323],"iteration":659,"passed_time":1.084493643,"remaining_time":0.5586785431},
{"learn":[0.1321194361],"iteration":660,"passed_time":1.085730712,"remaining_time":0.5568270976},
{"learn":[0.1320110935],"iteration":661,"passed_time":1.086955373,"remaining_time":0.5549711721},
{"learn":[0.1318281899],"iteration":662,"passed_time":1.088443847,"remaining_time":0.5532512465},
{"learn":[0.1316308624],"iteration":663,"passed_time":1.090066746,"remaining_time":0.5516000401},
{"learn":[0.1314109871],"iteration":664,"passed_time":1.091478672,"remaining_time":0.5498426394},
{"learn":[0.1312049585],"iteration":665,"passed_time":1.092855919,"remaining_time":0.5480688842},
{"learn":[0.1310480845],"iteration":666,"passed_time":1.094254869,"remaining_time":0.5463071533},
{"learn":[0.1308614816],"iteration":667,"passed_time":1.095616305,"remaining_time":0.5445278641},
{"learn":[0.1306281899],"iteration":668,"passed_time":1.096851962,"remaining_time":0.5426875923},
{"learn":[0.1304162923],"iteration":669,"passed_time":1.098203892,"remaining_time":0.5409063947},
{"learn":[0.1303403825],"iteration":670,"passed_time":1.099551002,"remaining_time":0.5391241129},
{"learn":[0.13012867],"iteration":671,"passed_time":1.101033952,"remaining_time":0.5374094291},
{"learn":[0.1299455401],"iteration":672,"passed_time":1.103244797,"remaining_time":0.5360491062},
{"learn":[0.1298563343],"iteration":673,"passed_time":1.104934738,"remaining_time":0.5344343094},
{"learn":[0.1296489815],"iteration":674,"passed_time":1.10632871,"remaining_time":0.5326767864},
{"learn":[0.1295571682],"iteration":675,"passed_time":1.107647998,"remaining_time":0.5308845436},
{"learn":[0.1294144191],"iteration":676,"passed_time":1.109051977,"remaining_time":0.5291341044},
{"learn":[0.1292165885],"iteration":677,"passed_time":1.110400942,"remaining_time":0.5273585596},
{"learn":[0.1289678792],"iteration":678,"passed_time":1.111831581,"remaining_time":0.5256228828},
{"learn":[0.128770484],"iteration":679,"passed_time":1.113549014,"remaining_time":0.5240230656},
{"learn":[0.128607694],"iteration":680,"passed_time":1.115952017,"remaining_time":0.5227440431},
{"learn":[0.1283911861],"iteration":681,"passed_time":1.117625952,"remaining_time":0.521121778},
{"learn":[0.1283437461],"iteration":682,"passed_time":1.118945357,"remaining_time":0.5193348142},
{"learn":[0.1281827994],"iteration":683,"passed_time":1.120430933,"remaining_time":0.5176259867},
{"learn":[0.1279915161],"iteration":684,"passed_time":1.121780949,"remaining_time":0.5158554728},
{"learn":[0.1278671776],"iteration":685,"passed_time":1.1229295,"remaining_time":0.5139939693},
{"learn":[0.1277366237],"iteration":686,"passed_time":1.12416314,"remaining_time":0.5121733083},
{"learn":[0.1276579358],"iteration":687,"passed_time":1.125324175,"remaining_time":0.510321428},
{"learn":[0.1274739388],"iteration":688,"passed_time":1.127070416,"remaining_time":0.5087357031},
{"learn":[0.1273776714],"iteration":689,"passed_time":1.128728729,"remaining_time":0.5071100087},
{"learn":[0.1270154387],"iteration":690,"passed_time":1.130500659,"remaining_time":0.5055350269},
{"learn":[0.1268084701],"iteration":691,"passed_time":1.131863906,"remaining_time":0.5037775765},
{"learn":[0.1267241932],"iteration":692,"passed_time":1.133046836,"remaining_time":0.5019413834},
{"learn":[0.1265497057],"iteration":693,"passed_time":1.134281294,"remaining_time":0.5001297924},
{"learn":[0.1264031168],"iteration":694,"passed_time":1.13546486,"remaining_time":0.4982975286},
{"learn":[0.1262945022],"iteration":695,"passed_time":1.136638977,"remaining_time":0.4964630016},
{"learn":[0.1261658989],"iteration":696,"passed_time":1.137860889,"remaining_time":0.4946511467},
{"learn":[0.1260704133],"iteration":697,"passed_time":1.139228915,"remaining_time":0.4929042012},
{"learn":[0.1259413586],"iteration":698,"passed_time":1.140501047,"remaining_time":0.4911170459},
{"learn":[0.1258334238],"iteration":699,"passed_time":1.142357387,"remaining_time":0.4895817375},
{"learn":[0.1257512046],"iteration":700,"passed_time":1.143993027,"remaining_time":0.4879513767},
{"learn":[0.1257304166],"iteration":701,"passed_time":1.145136255,"remaining_time":0.4861119715},
{"learn":[0.1255649571],"iteration":702,"passed_time":1.146344048,"remaining_time":0.4843018241},
{"learn":[0.1255316472],"iteration":703,"passed_time":1.147576464,"remaining_time":0.4825037407},
{"learn":[0.1252765116],"iteration":704,"passed_time":1.148790625,"remaining_time":0.4806996232},
{"learn":[0.1251558222],"iteration":705,"passed_time":1.150008083,"remaining_time":0.47889855},
{"learn":[0.1249451096],"iteration":706,"passed_time":1.151275218,"remaining_time":0.4771197154},
{"learn":[0.1246848098],"iteration":707,"passed_time":1.152536356,"remaining_time":0.4753398532},
{"learn":[0.1245662844],"iteration":708,"passed_time":1.153810875,"remaining_time":0.4735669457},
{"learn":[0.1244950995],"iteration":709,"passed_time":1.155657555,"remaining_time":0.4720291422},
{"learn":[0.1242593093],"iteration":710,"passed_time":1.157151763,"remaining_time":0.4703472004},
{"learn":[0.1241292994],"iteration":711,"passed_time":1.158360677,"remaining_time":0.4685503863},
{"learn":[0.1239149511],"iteration":712,"passed_time":1.159631405,"remaining_time":0.4667801027},
{"learn":[0.1238420654],"iteration":713,"passed_time":1.160892542,"remaining_time":0.4650073766},
{"learn":[0.1237606078],"iteration":714,"passed_time":1.162097807,"remaining_time":0.4632138113},
{"learn":[0.12364504],"iteration":715,"passed_time":1.163433981,"remaining_time":0.4614738138},
{"learn":[0.123547569],"iteration":716,"passed_time":1.164657166,"remaining_time":0.4596903461},
{"learn":[0.1233777123],"iteration":717,"passed_time":1.165917859,"remaining_time":0.4579231704},
{"learn":[0.1231266312],"iteration":718,"passed_time":1.167221031,"remaining_time":0.4561740051},
{"learn":[0.1229709021],"iteration":719,"passed_time":1.168939352,"remaining_time":0.4545875257},
{"learn":[0.1228896159],"iteration":720,"passed_time":1.170425486,"remaining_time":0.452910833},
{"learn":[0.1227418393],"iteration":721,"passed_time":1.171683109,"remaining_time":0.4511466819},
{"learn":[0.1225487069],"iteration":722,"passed_time":1.172929083,"remaining_time":0.4493794689},
{"learn":[0.1223430306],"iteration":723,"passed_time":1.174155404,"remaining_time":0.4476062036},
{"learn":[0.122252122],"iteration":724,"passed_time":1.175419241,"remaining_time":0.4458486777},
{"learn":[0.1219891171],"iteration":725,"passed_time":1.176662344,"remaining_time":0.4440846864},
{"learn":[0.1217050486],"iteration":726,"passed_time":1.17783124,"remaining_time":0.4422942621},
{"learn":[0.1216034116],"iteration":727,"passed_time":1.179050495,"remaining_time":0.4405243609},
{"learn":[0.1214799965],"iteration":728,"passed_time":1.180308178,"remaining_time":0.4387702556},
{"learn":[0.1212236415],"iteration":729,"passed_time":1.182079691,"remaining_time":0.437207557},
{"learn":[0.1210169525],"iteration":730,"passed_time":1.183679459,"remaining_time":0.435581087},
{"learn":[0.1208823848],"iteration":731,"passed_time":1.184941047,"remaining_time":0.433830875},
{"learn":[0.1207454814],"iteration":732,"passed_time":1.186155332,"remaining_time":0.4320647662},
{"learn":[0.1206010627],"iteration":733,"passed_time":1.187411331,"remaining_time":0.4303152779},
{"learn":[0.1205714566],"iteration":734,"passed_time":1.188667222,"remaining_time":0.4285670936},
{"learn":[0.1204894027],"iteration":735,"passed_time":1.18982015,"remaining_time":0.4267833147},
{"learn":[0.1203338102],"iteration":736,"passed_time":1.191057283,"remaining_time":0.4250312963},
{"learn":[0.1202186324],"iteration":737,"passed_time":1.192268194,"remaining_time":0.4232713642},
{"learn":[0.1201440227],"iteration":738,"passed_time":1.193572822,"remaining_time":0.421546017},
{"learn":[0.1199825131],"iteration":739,"passed_time":1.195300517,"remaining_time":0.4199704518},
{"learn":[0.1197929987],"iteration":740,"passed_time":1.196764913,"remaining_time":0.4183024459},
{"learn":[0.1197338995],"iteration":741,"passed_time":1.198021317,"remaining_time":0.4165626683},
{"learn":[0.119650341],"iteration":742,"passed_time":1.199219278,"remaining_time":0.4148039765},
{"learn":[0.1195380328],"iteration":743,"passed_time":1.200465269,"remaining_time":0.4130633185},
{"learn":[0.119458025],"iteration":744,"passed_time":1.201712943,"remaining_time":0.4113245642},
{"learn":[0.1192793108],"iteration":745,"passed_time":1.202935337,"remaining_time":0.4095785197},
{"learn":[0.1191013448],"iteration":746,"passed_time":1.204141248,"remaining_time":0.407828294},
{"learn":[0.1189961116],"iteration":747,"passed_time":1.205377524,"remaining_time":0.4060897541},
{"learn":[0.1188912302],"iteration":748,"passed_time":1.206641089,"remaining_time":0.4043616999},
{"learn":[0.1187004961],"iteration":749,"passed_time":1.208473384,"remaining_time":0.4028244612},
{"learn":[0.1185705669],"iteration":750,"passed_time":1.209999945,"remaining_time":0.4011850685},
{"learn":[0.1184910641],"iteration":751,"passed_time":1.211207403,"remaining_time":0.3994407392},
{"learn":[0.1183743442],"iteration":752,"passed_time":1.212513372,"remaining_time":0.3977301499},
{"learn":[0.1182826688],"iteration":753,"passed_time":1.213730505,"remaining_time":0.3959916503},
{"learn":[0.1180673442],"iteration":754,"passed_time":1.214988208,"remaining_time":0.3942676966},
{"learn":[0.1179238981],"iteration":755,"passed_time":1.216230163,"remaining_time":0.392539894},
{"learn":[0.1178924924],"iteration":756,"passed_time":1.217398549,"remaining_time":0.3907897587},
{"learn":[0.1177057937],"iteration":757,"passed_time":1.21863903,"remaining_time":0.3890641757},
{"learn":[0.1174831772],"iteration":758,"passed_time":1.219950237,"remaining_time":0.3873623281},
{"learn":[0.1173178852],"iteration":759,"passed_time":1.221793503,"remaining_time":0.3858295273},
{"learn":[0.1171816248],"iteration":760,"passed_time":1.223284601,"remaining_time":0.3841853083},
{"learn":[0.1170969152],"iteration":761,"passed_time":1.224884156,"remaining_time":0.3825753664},
{"learn":[0.1169577509],"iteration":762,"passed_time":1.226084812,"remaining_time":0.380841547},
{"learn":[0.116780265],"iteration":763,"passed_time":1.227301325,"remaining_time":0.3791140218},
{"learn":[0.1166826687],"iteration":764,"passed_time":1.228512737,"remaining_time":0.3773862655},
{"learn":[0.1165644559],"iteration":765,"passed_time":1.22968472,"remaining_time":0.3756478125},
{"learn":[0.1163187898],"iteration":766,"passed_time":1.230865192,"remaining_time":0.3739134154},
{"learn":[0.1162140279],"iteration":767,"passed_time":1.232049041,"remaining_time":0.3721814812},
{"learn":[0.1160660467],"iteration":768,"passed_time":1.233341755,"remaining_time":0.3704836743},
{"learn":[0.1159125424],"iteration":769,"passed_time":1.235202348,"remaining_time":0.3689565456},
{"learn":[0.1158585523],"iteration":770,"passed_time":1.236710197,"remaining_time":0.3673237809},
{"learn":[0.1156018307],"iteration":771,"passed_time":1.238032534,"remaining_time":0.3656365515},
{"learn":[0.1154332162],"iteration":772,"passed_time":1.239261404,"remaining_time":0.3639228184},
{"learn":[0.1152647456],"iteration":773,"passed_time":1.240471396,"remaining_time":0.3622048262},
{"learn":[0.1150885482],"iteration":774,"passed_time":1.241727579,"remaining_time":0.3605015552},
{"learn":[0.1149604827],"iteration":775,"passed_time":1.243020639,"remaining_time":0.3588100815},
{"learn":[0.1147391333],"iteration":776,"passed_time":1.244256198,"remaining_time":0.3571031302},
{"learn":[0.1146877097],"iteration":777,"passed_time":1.245419577,"remaining_time":0.3553767945},
{"learn":[0.1143754292],"iteration":778,"passed_time":1.246582995,"remaining_time":0.3536519152},
{"learn":[0.114204101],"iteration":779,"passed_time":1.248260252,"remaining_time":0.3520734044},
{"learn":[0.1140567908],"iteration":780,"passed_time":1.249945371,"remaining_time":0.3504968454},
{"learn":[0.1139607053],"iteration":781,"passed_time":1.251275243,"remaining_time":0.3488209757},
{"learn":[0.1137400888],"iteration":782,"passed_time":1.252522825,"remaining_time":0.347123184},
{"learn":[0.1136346156],"iteration":783,"passed_time":1.253786827,"remaining_time":0.3454310646},
{"learn":[0.1135050496],"iteration":784,"passed_time":1.255075759,"remaining_time":0.3437468639},
{"learn":[0.1134235529],"iteration":785,"passed_time":1.256259013,"remaining_time":0.3420348968},
{"learn":[0.1133286925],"iteration":786,"passed_time":1.257446099,"remaining_time":0.3403253102},
{"learn":[0.1131767534],"iteration":787,"passed_time":1.258669339,"remaining_time":0.3386267764},
{"learn":[0.1131015665],"iteration":788,"passed_time":1.259841243,"remaining_time":0.3369157189},
{"learn":[0.1129948136],"iteration":789,"passed_time":1.261618353,"remaining_time":0.335366904},
{"learn":[0.1128591313],"iteration":790,"passed_time":1.26310587,"remaining_time":0.3337409948},
{"learn":[0.1127184709],"iteration":791,"passed_time":1.26439366,"remaining_time":0.3320629813},
{"learn":[0.1127009536],"iteration":792,"passed_time":1.265601212,"remaining_time":0.3303650075},
{"learn":[0.1125344877],"iteration":793,"passed_time":1.266836824,"remaining_time":0.3286755487},
{"learn":[0.1123770793],"iteration":794,"passed_time":1.268116285,"remaining_time":0.3269985388},
{"learn":[0.1122211182],"iteration":795,"passed_time":1.269339255,"remaining_time":0.3253080502},
{"learn":[0.1120265376],"iteration":796,"passed_time":1.270568141,"remaining_time":0.3236202418},
{"learn":[0.1119093763],"iteration":797,"passed_time":1.27176169,"remaining_time":0.3219246383},
{"learn":[0.1117635143],"iteration":798,"passed_time":1.273030141,"remaining_time":0.3202491343},
{"learn":[0.1116027681],"iteration":799,"passed_time":1.274920113,"remaining_time":0.3187300283},
{"learn":[0.1115455442],"iteration":800,"passed_time":1.276389928,"remaining_time":0.3171056125},
{"learn":[0.1113683761],"iteration":801,"passed_time":1.277646493,"remaining_time":0.3154289347},
{"learn":[0.1111963085],"iteration":802,"passed_time":1.27889043,"remaining_time":0.3137502052},
{"learn":[0.1110053118],"iteration":803,"passed_time":1.280184732,"remaining_time":0.3120848351},
{"learn":[0.1109326719],"iteration":804,"passed_time":1.281298474,"remaining_time":0.3103766489},
{"learn":[0.1108479035],"iteration":805,"passed_time":1.282479844,"remaining_time":0.3086862157},
{"learn":[0.1107485426],"iteration":806,"passed_time":1.283724017,"remaining_time":0.3070120634},
{"learn":[0.1106632348],"iteration":807,"passed_time":1.284928081,"remaining_time":0.305329445},
{"learn":[0.1105731807],"iteration":808,"passed_time":1.286141678,"remaining_time":0.3036502602},
{"learn":[0.1104541062],"iteration":809,"passed_time":1.287910299,"remaining_time":0.3021024157},
{"learn":[0.1103136321],"iteration":810,"passed_time":1.289401716,"remaining_time":0.3004894258},
{"learn":[0.1102075326],"iteration":811,"passed_time":1.29075918,"remaining_time":0.2988457215},
{"learn":[0.1100628851],"iteration":812,"passed_time":1.291994804,"remaining_time":0.2971746966},
{"learn":[0.1099684558],"iteration":813,"passed_time":1.293280688,"remaining_time":0.2955162261},
{"learn":[0.1098821097],"iteration":814,"passed_time":1.294448173,"remaining_time":0.2938317938},
{"learn":[0.1098371441],"iteration":815,"passed_time":1.295667312,"remaining_time":0.2921602763},
{"learn":[0.1096580468],"iteration":816,"passed_time":1.296936224,"remaining_time":0.2905010148},
{"learn":[0.1094002743],"iteration":817,"passed_time":1.298170021,"remaining_time":0.2888348948},
{"learn":[0.1091461405],"iteration":818,"passed_time":1.299555183,"remaining_time":0.2872032822},
{"learn":[0.108919027],"iteration":819,"passed_time":1.30127418,"remaining_time":0.2856455516},
{"learn":[0.1087252148],"iteration":820,"passed_time":1.302845634,"remaining_time":0.2840552599},
{"learn":[0.1086408501],"iteration":821,"passed_time":1.304273927,"remaining_time":0.2824340134},
{"learn":[0.1086100411],"iteration":822,"passed_time":1.305603315,"remaining_time":0.2807919645},
{"learn":[0.1083346414],"iteration":823,"passed_time":1.306933275,"remaining_time":0.2791507967},
{"learn":[0.1083015496],"iteration":824,"passed_time":1.308729571,"remaining_time":0.2776093029},
{"learn":[0.1081243025],"iteration":825,"passed_time":1.310572223,"remaining_time":0.2760769574},
{"learn":[0.1079493501],"iteration":826,"passed_time":1.312145229,"remaining_time":0.2744874542},
{"learn":[0.1078288604],"iteration":827,"passed_time":1.313396755,"remaining_time":0.27283121},
{"learn":[0.1077693473],"iteration":828,"passed_time":1.314623371,"remaining_time":0.2711708039},
{"learn":[0.1076169392],"iteration":829,"passed_time":1.315820384,"remaining_time":0.2695053798},
{"learn":[0.1075096709],"iteration":830,"passed_time":1.317010619,"remaining_time":0.2678397046},
{"learn":[0.1075068278],"iteration":831,"passed_time":1.31777515,"remaining_time":0.2660892129},
{"learn":[0.1073585351],"iteration":832,"passed_time":1.319012387,"remaining_time":0.2644358568},
{"learn":[0.1072190823],"iteration":833,"passed_time":1.320278836,"remaining_time":0.2627893126},
{"learn":[0.1071382975],"iteration":834,"passed_time":1.321542555,"remaining_time":0.2611431395},
{"learn":[0.1070270515],"iteration":835,"passed_time":1.323200698,"remaining_time":0.2595752565},
{"learn":[0.1070076814],"iteration":836,"passed_time":1.324208741,"remaining_time":0.2578805553},
{"learn":[0.1068784714],"iteration":837,"passed_time":1.325493508,"remaining_time":0.2562409884},
{"learn":[0.1067884778],"iteration":838,"passed_time":1.326737414,"remaining_time":0.2545944264},
{"learn":[0.1066083846],"iteration":839,"passed_time":1.328040302,"remaining_time":0.2529600575},
{"learn":[0.1064666638],"iteration":840,"passed_time":1.329261759,"remaining_time":0.2513110816},
{"learn":[0.1063328978],"iteration":841,"passed_time":1.330479746,"remaining_time":0.2496624701},
{"learn":[0.1061561831],"iteration":842,"passed_time":1.331881123,"remaining_time":0.2480490347},
{"learn":[0.1060946858],"iteration":843,"passed_time":1.333119761,"remaining_time":0.2464060221},
{"learn":[0.1059104973],"iteration":844,"passed_time":1.334292796,"remaining_time":0.244751933},
{"learn":[0.1057436414],"iteration":845,"passed_time":1.336229966,"remaining_time":0.2432380789},
{"learn":[0.1057359001],"iteration":846,"passed_time":1.337680353,"remaining_time":0.241635294},
{"learn":[0.1055965247],"iteration":847,"passed_time":1.338925007,"remaining_time":0.2399959918},
{"learn":[0.1054429986],"iteration":848,"passed_time":1.340195392,"remaining_time":0.2383621957},
{"learn":[0.1052639067],"iteration":849,"passed_time":1.341451023,"remaining_time":0.2367266512},
{"learn":[0.1051539832],"iteration":850,"passed_time":1.342778356,"remaining_time":0.2351045535},
{"learn":[0.105112507],"iteration":851,"passed_time":1.344098256,"remaining_time":0.2334818567},
{"learn":[0.1050608796],"iteration":852,"passed_time":1.345386465,"remaining_time":0.2318544084},
{"learn":[0.1049265803],"iteration":853,"passed_time":1.346593641,"remaining_time":0.2302139011},
{"learn":[0.1048814819],"iteration":854,"passed_time":1.347861554,"remaining_time":0.228584708},
{"learn":[0.1047641004],"iteration":855,"passed_time":1.349748016,"remaining_time":0.2270604138},
{"learn":[0.1045955646],"iteration":856,"passed_time":1.351161486,"remaining_time":0.2254563507},
{"learn":[0.1045234995],"iteration":857,"passed_time":1.352389379,"remaining_time":0.2238220185},
{"learn":[0.1044231523],"iteration":858,"passed_time":1.353598368,"remaining_time":0.2221855296},
{"learn":[0.1042492793],"iteration":859,"passed_time":1.354837806,"remaining_time":0.2205549917},
{"learn":[0.1040948399],"iteration":860,"passed_time":1.356095841,"remaining_time":0.2189283646},
{"learn":[0.103967679],"iteration":861,"passed_time":1.357430281,"remaining_time":0.2173148246},
{"learn":[0.1038321892],"iteration":862,"passed_time":1.358632656,"remaining_time":0.2156809663},
{"learn":[0.1036414343],"iteration":863,"passed_time":1.3599859,"remaining_time":0.2140718546},
{"learn":[0.1035548353],"iteration":864,"passed_time":1.361365549,"remaining_time":0.2124674557},
{"learn":[0.1035058556],"iteration":865,"passed_time":1.362951868,"remaining_time":0.2108955546},
{"learn":[0.1034310283],"iteration":866,"passed_time":1.364306367,"remaining_time":0.2092880586},
{"learn":[0.1032710762],"iteration":867,"passed_time":1.36548238,"remaining_time":0.2076540025},
{"learn":[0.1030652158],"iteration":868,"passed_time":1.366745981,"remaining_time":0.2060342042},
{"learn":[0.1029974994],"iteration":869,"passed_time":1.367958233,"remaining_time":0.2044075521},
{"learn":[0.102873891],"iteration":870,"passed_time":1.369226607,"remaining_time":0.2027901634},
{"learn":[0.1027066029],"iteration":871,"passed_time":1.370535543,"remaining_time":0.2011795292},
{"learn":[0.102678084],"iteration":872,"passed_time":1.371778949,"remaining_time":0.1995600533},
{"learn":[0.1025876952],"iteration":873,"passed_time":1.373095426,"remaining_time":0.1979519721},
{"learn":[0.1025515447],"iteration":874,"passed_time":1.374474212,"remaining_time":0.1963534588},
{"learn":[0.1024191193],"iteration":875,"passed_time":1.376048095,"remaining_time":0.1947830636},
{"learn":[0.1022245202],"iteration":876,"passed_time":1.377548073,"remaining_time":0.1932022953},
{"learn":[0.1021094955],"iteration":877,"passed_time":1.378812131,"remaining_time":0.1915889294},
{"learn":[0.1021022506],"iteration":878,"passed_time":1.380138918,"remaining_time":0.1899849932},
{"learn":[0.101996565],"iteration":879,"passed_time":1.381416858,"remaining_time":0.1883750261},
{"learn":[0.1018371178],"iteration":880,"passed_time":1.38272313,"remaining_time":0.1867696395},
{"learn":[0.1016837358],"iteration":881,"passed_time":1.384043347,"remaining_time":0.185166797},
{"learn":[0.1015860348],"iteration":882,"passed_time":1.385365549,"remaining_time":0.1835648576},
{"learn":[0.1014740894],"iteration":883,"passed_time":1.386683987,"remaining_time":0.1819630571},
{"learn":[0.1013390825],"iteration":884,"passed_time":1.388492943,"remaining_time":0.1804256366},
{"learn":[0.1013342923],"iteration":885,"passed_time":1.389325045,"remaining_time":0.1787619132},
{"learn":[0.1012712466],"iteration":886,"passed_time":1.390696788,"remaining_time":0.1771688129},
{"learn":[0.1011817289],"iteration":887,"passed_time":1.392056248,"remaining_time":0.175574662},
{"learn":[0.1010456184],"iteration":888,"passed_time":1.393389591,"remaining_time":0.173977778},
{"learn":[0.1008842363],"iteration":889,"passed_time":1.394613304,"remaining_time":0.1723679365},
{"learn":[0.1006787323],"iteration":890,"passed_time":1.395790386,"remaining_time":0.1707532571},
{"learn":[0.100548895],"iteration":891,"passed_time":1.39695356,"remaining_time":0.169137875},
{"learn":[0.100454996],"iteration":892,"passed_time":1.398156252,"remaining_time":0.1675282407},
{"learn":[0.1002354673],"iteration":893,"passed_time":1.399385746,"remaining_time":0.1659226947},
{"learn":[0.1001313505],"iteration":894,"passed_time":1.401066496,"remaining_time":0.1643709297},
{"learn":[0.1000551206],"iteration":895,"passed_time":1.402640504,"remaining_time":0.162806487},
{"learn":[0.09994035785],"iteration":896,"passed_time":1.404093669,"remaining_time":0.161228147},
{"learn":[0.09980180784],"iteration":897,"passed_time":1.405458505,"remaining_time":0.159640053},
{"learn":[0.09976010833],"iteration":898,"passed_time":1.406768397,"remaining_time":0.1580462827},
{"learn":[0.09963443353],"iteration":899,"passed_time":1.407976429,"remaining_time":0.1564418255},
{"learn":[0.09956213297],"iteration":900,"passed_time":1.409133231,"remaining_time":0.1548326191},
{"learn":[0.09942770723],"iteration":901,"passed_time":1.410373545,"remaining_time":0.1532334894},
{"learn":[0.09932107328],"iteration":902,"passed_time":1.411617107,"remaining_time":0.1516355032},
{"learn":[0.0992286745],"iteration":903,"passed_time":1.412781202,"remaining_time":0.1500298622},
{"learn":[0.09909961156],"iteration":904,"passed_time":1.414680556,"remaining_time":0.1485023788},
{"learn":[0.0989801917],"iteration":905,"passed_time":1.416261491,"remaining_time":0.1469410377},
{"learn":[0.09889731672],"iteration":906,"passed_time":1.41761357,"remaining_time":0.1453561874},
{"learn":[0.09863068606],"iteration":907,"passed_time":1.418872535,"remaining_time":0.1437624154},
{"learn":[0.09855350522],"iteration":908,"passed_time":1.420206413,"remaining_time":0.1421768796},
{"learn":[0.09853583971],"iteration":909,"passed_time":1.421496192,"remaining_time":0.1405875354},
{"learn":[0.0983974384],"iteration":910,"passed_time":1.422890848,"remaining_time":0.1390090949},
{"learn":[0.09826800071],"iteration":911,"passed_time":1.424294371,"remaining_time":0.137431913},
{"learn":[0.09808823279],"iteration":912,"passed_time":1.425547741,"remaining_time":0.1358408034},
{"learn":[0.09789968438],"iteration":913,"passed_time":1.426782409,"remaining_time":0.1342486731},
{"learn":[0.09775885051],"iteration":914,"passed_time":1.428480055,"remaining_time":0.132700333},
{"learn":[0.09772364743],"iteration":915,"passed_time":1.429978208,"remaining_time":0.1311333728},
{"learn":[0.09762799217],"iteration":916,"passed_time":1.431412892,"remaining_time":0.1295608179},
{"learn":[0.09748685637],"iteration":917,"passed_time":1.432576784,"remaining_time":0.127964375},
{"learn":[0.09729824453],"iteration":918,"passed_time":1.433833044,"remaining_time":0.1263770148},
{"learn":[0.0972350104],"iteration":919,"passed_time":1.434761473,"remaining_time":0.1247618672},
{"learn":[0.09714224083],"iteration":920,"passed_time":1.435907545,"remaining_time":0.1231668795},
{"learn":[0.09691433505],"iteration":921,"passed_time":1.437159644,"remaining_time":0.1215818354},
{"learn":[0.09687277934],"iteration":922,"passed_time":1.438334206,"remaining_time":0.1199910443},
{"learn":[0.09667366442],"iteration":923,"passed_time":1.439542721,"remaining_time":0.1184039468},
{"learn":[0.0965494895],"iteration":924,"passed_time":1.44131154,"remaining_time":0.1168630978},
{"learn":[0.0963941375],"iteration":925,"passed_time":1.44287187,"remaining_time":0.1153050955},
{"learn":[0.09630212913],"iteration":926,"passed_time":1.444142913,"remaining_time":0.1137243071},
{"learn":[0.09615332201],"iteration":927,"passed_time":1.445448866,"remaining_time":0.1121468948},
{"learn":[0.09608324459],"iteration":928,"passed_time":1.446676102,"remaining_time":0.1105640508},
{"learn":[0.09591842612],"iteration":929,"passed_time":1.447917284,"remaining_time":0.1089830213},
{"learn":[0.09582979398],"iteration":930,"passed_time":1.449115412,"remaining_time":0.107399531},
{"learn":[0.09576346079],"iteration":931,"passed_time":1.450311715,"remaining_time":0.1058167346},
{"learn":[0.09560355407],"iteration":932,"passed_time":1.451504379,"remaining_time":0.1042345053},
{"learn":[0.09553052565],"iteration":933,"passed_time":1.452743113,"remaining_time":0.1026563656},
{"learn":[0.09548131035],"iteration":934,"passed_time":1.454359478,"remaining_time":0.1011052044},
{"learn":[0.09531948176],"iteration":935,"passed_time":1.456104003,"remaining_time":0.09956266689},
{"learn":[0.09521071],"iteration":936,"passed_time":1.457446641,"remaining_time":0.09799267701},
{"learn":[0.09508776466],"iteration":937,"passed_time":1.458651564,"remaining_time":0.09641406925},
{"learn":[0.09497875331],"iteration":938,"passed_time":1.459892563,"remaining_time":0.094838601},
{"learn":[0.0949269317],"iteration":939,"passed_time":1.461067136,"remaining_time":0.09325960439},
{"learn":[0.0947982376],"iteration":940,"passed_time":1.462256669,"remaining_time":0.09168240537},
{"learn":[0.09464189917],"iteration":941,"passed_time":1.463447823,"remaining_time":0.09010612921},
{"learn":[0.09443213099],"iteration":942,"passed_time":1.464656283,"remaining_time":0.08853171596},
{"learn":[0.09443043892],"iteration":943,"passed_time":1.465210327,"remaining_time":0.0869192567},
{"learn":[0.09425523325],"iteration":944,"passed_time":1.466472223,"remaining_time":0.08535023519},
{"learn":[0.0942077939],"iteration":945,"passed_time":1.468244231,"remaining_time":0.08381098147},
{"learn":[0.09414884251],"iteration":946,"passed_time":1.469734701,"remaining_time":0.08225547959},
{"learn":[0.09399331234],"iteration":947,"passed_time":1.470978653,"remaining_time":0.0806865928},
{"learn":[0.09395922209],"iteration":948,"passed_time":1.472208971,"remaining_time":0.07911765808},
{"learn":[0.09386944909],"iteration":949,"passed_time":1.473427304,"remaining_time":0.07754880549},
{"learn":[0.09379368251],"iteration":950,"passed_time":1.4746156,"remaining_time":0.07597914235},
{"learn":[0.09366688582],"iteration":951,"passed_time":1.475788166,"remaining_time":0.07440948735},
{"learn":[0.0934993147],"iteration":952,"passed_time":1.477032483,"remaining_time":0.07284420429},
{"learn":[0.09339884908],"iteration":953,"passed_time":1.478305965,"remaining_time":0.07128100041},
{"learn":[0.09325567271],"iteration":954,"passed_time":1.479687553,"remaining_time":0.06972349725},
{"learn":[0.09311217658],"iteration":955,"passed_time":1.482313795,"remaining_time":0.06822364748},
{"learn":[0.09291675514],"iteration":956,"passed_time":1.483739233,"remaining_time":0.06666748903},
{"learn":[0.09283082889],"iteration":957,"passed_time":1.484967795,"remaining_time":0.06510297222},
{"learn":[0.09279366881],"iteration":958,"passed_time":1.48620777,"remaining_time":0.06353964399},
{"learn":[0.09261463593],"iteration":959,"passed_time":1.487457761,"remaining_time":0.0619774067},
{"learn":[0.09252617796],"iteration":960,"passed_time":1.488694263,"remaining_time":0.06041527186},
{"learn":[0.09240726529],"iteration":961,"passed_time":1.489876856,"remaining_time":0.05885168453},
{"learn":[0.09236388514],"iteration":962,"passed_time":1.49112739,"remaining_time":0.0572914989},
{"learn":[0.09219783638],"iteration":963,"passed_time":1.492371224,"remaining_time":0.05573170548},
{"learn":[0.09211242477],"iteration":964,"passed_time":1.49376176,"remaining_time":0.05417788765},
{"learn":[0.09200268008],"iteration":965,"passed_time":1.495381116,"remaining_time":0.05263246162},
{"learn":[0.09191475971],"iteration":966,"passed_time":1.496827883,"remaining_time":0.0510809929},
{"learn":[0.09179752933],"iteration":967,"passed_time":1.498066894,"remaining_time":0.04952287252},
{"learn":[0.09167269028],"iteration":968,"passed_time":1.499260643,"remaining_time":0.04796396277},
{"learn":[0.09162464824],"iteration":969,"passed_time":1.500448383,"remaining_time":0.04640562009},
{"learn":[0.09156514197],"iteration":970,"passed_time":1.501696597,"remaining_time":0.04484984686},
{"learn":[0.09149368153],"iteration":971,"passed_time":1.502848972,"remaining_time":0.04329194569},
{"learn":[0.09143305034],"iteration":972,"passed_time":1.504108873,"remaining_time":0.04173786185},
{"learn":[0.09131200727],"iteration":973,"passed_time":1.505297126,"remaining_time":0.04018246947},
{"learn":[0.09118082947],"iteration":974,"passed_time":1.506571772,"remaining_time":0.03863004542},
{"learn":[0.09104927112],"iteration":975,"passed_time":1.508408713,"remaining_time":0.03709201754},
{"learn":[0.09092682878],"iteration":976,"passed_time":1.509829033,"remaining_time":0.03554356987},
{"learn":[0.09083011735],"iteration":977,"passed_time":1.511133187,"remaining_time":0.03399277107},
{"learn":[0.09068974367],"iteration":978,"passed_time":1.51247083,"remaining_time":0.0324431945},
{"learn":[0.09059968327],"iteration":979,"passed_time":1.513668374,"remaining_time":0.03089119132},
{"learn":[0.0905549663],"iteration":980,"passed_time":1.514835334,"remaining_time":0.0293393184},
{"learn":[0.0904802639],"iteration":981,"passed_time":1.516036874,"remaining_time":0.02778886327},
{"learn":[0.09036850036],"iteration":982,"passed_time":1.517274425,"remaining_time":0.02623974082},
{"learn":[0.09026816999],"iteration":983,"passed_time":1.51849809,"remaining_time":0.02469102585},
{"learn":[0.09020251922],"iteration":984,"passed_time":1.519737067,"remaining_time":0.02314320407},
{"learn":[0.09004867765],"iteration":985,"passed_time":1.521771118,"remaining_time":0.02160729782},
{"learn":[0.08995751213],"iteration":986,"passed_time":1.523276207,"remaining_time":0.02006341509},
{"learn":[0.0899442474],"iteration":987,"passed_time":1.524473635,"remaining_time":0.01851587411},
{"learn":[0.08982960344],"iteration":988,"passed_time":1.525688321,"remaining_time":0.01696923309},
{"learn":[0.08969654365],"iteration":989,"passed_time":1.526899289,"remaining_time":0.01542322514},
{"learn":[0.08964411297],"iteration":990,"passed_time":1.528111453,"remaining_time":0.01387790421},
{"learn":[0.08955714685],"iteration":991,"passed_time":1.529485786,"remaining_time":0.01233456279},
{"learn":[0.08945601371],"iteration":992,"passed_time":1.530662143,"remaining_time":0.01079016616},
{"learn":[0.08939214743],"iteration":993,"passed_time":1.531901358,"remaining_time":0.009246889486},
{"learn":[0.08929106446],"iteration":994,"passed_time":1.533214921,"remaining_time":0.007704597594},
{"learn":[0.08925945784],"iteration":995,"passed_time":1.535030331,"remaining_time":0.006164780444},
{"learn":[0.0892173268],"iteration":996,"passed_time":1.536670289,"remaining_time":0.004623882514},
{"learn":[0.08913759607],"iteration":997,"passed_time":1.537932856,"remaining_time":0.003082029771},
{"learn":[0.08899452133],"iteration":998,"passed_time":1.539165089,"remaining_time":0.001540705795},
{"learn":[0.0888439794],"iteration":999,"passed_time":1.540380907,"remaining_time":0}
]}